Workbook

Sheet Read Me
B1: Paytm Innovation Challenge 2026 – Round 1 VOC workbook
B2: Kartik Raj | IIT Kanpur | Individual entry | Track B: Grow Paytm usage among merchants as UPI payers
B4: What this workbook contains
B5: 1. VOC Collection – the official template (columns A–L unchanged) plus Track B columns M–AH. One row per respondent, VOC-001 to VOC-050.
B6: 2. VOC Dashboard – live counts and ₹ figures calculated from the VOC rows: sample quality, the 'leak', GMV by app and use case, barriers, concept test.
B7: 3. Opportunity Sizing – the funnel, Year 1–3 impact on MTU, GMV, frequency and revenue, and the 90-day Kanpur pilot. Inputs are blue with sources.
B8: 4. Field Guide – the 5-minute and 15-minute interview scripts, sampling plan and one example row.
B9: 5. Sources – every external number used.
B11: Colour legend
B12: Light-yellow cells = interview inputs. Grey 'CALC' columns = formulas. Blue numbers (Opportunity Sizing) = assumptions, each with its source.
B14: Who was interviewed (Track B)
B15: Respondents are shop owners or the person who decides how suppliers are paid, not cashiers. Questions anchored on the last few real supplier payments (app, amount, frequency), not on what they 'would' do.

Sheet VOC Collection
A1: Paytm UPI VOC collection | Kartik Raj (Individual) | Track B: Merchants as UPI payers
A2: Columns A–L follow the template; columns M–AH add Track B detail. Grey CALC columns are formulas. All respondents are anonymised: area and shop type only, no names or numbers.
A4: VOC ID | B4: Date | C4: Respondent type | D4: City / area | E4: Profile / category | F4: UPI apps used (you can mention multiple apps if used for different purposes/occasions) | G4: Primary UPI app used | H4: Why was it chosen? (exact words) | I4: When or why is Paytm used? Or not used if switched from Paytm? | J4: Need, barrier or motivation to switch (derived from the conversation, not a direct question - maybe a feature, campaign, perception etc.) | K4: Opportunity / idea | L4: Key quote | M4: Interview type | N4: Who decides supplier payments? | O4: Customers pay this shop mostly via | P4: Supplier payments made from | Q4: Est. monthly stock purchase (₹) | R4: Use case 1 | S4: UC1 payments / month | T4: UC1 typical amount (₹) | U4: UC1 paid with | V4: Use case 2 | W4: UC2 payments / month | X4: UC2 typical amount (₹) | Y4: UC2 paid with | Z4: Use case 3 | AA4: UC3 payments / month | AB4: UC3 typical amount (₹) | AC4: UC3 paid with | AD4: Main barrier to paying suppliers on Paytm (coded) | AE4: Knew Paytm can pay suppliers? | AF4: Reaction: 'supplier bills show up inside Paytm, pay in 1 tap' (1–5) | AG4: Would use 7-day pay-later for stock? | AH4: Any supplier asked for cash / bank transfer instead of QR recently? | AI4: CALC: Business UPI paid / month (₹) | AJ4: CALC: Paid via Paytm / month (₹) | AK4: CALC: Paytm share of business UPI | AL4: CALC: 'Leak' flag (receives on Paytm, pays suppliers mostly elsewhere)
A5: VOC-001 | B5: 46289 | C5: Merchant | D5: IITK Shopping Complex | E5: Kirana / grocery | F5: PhonePe for stock bills; Cash for staff salary | G5: PhonePe | H5: Paytm sirf aane ke liye hai, dena ho toh PhonePe khulta hai naturally. | I5: Customers pay on Paytm Soundbox; receiving only, no supplier payment goes through Paytm. Did not know Paytm can pay suppliers. | J5: Habit: other app is default | K5: Put the supplier bill inside Paytm + Soundbox reminder so Paytm becomes the default place to pay; keen on pay-later | L5: Paytm sirf aane ke liye hai, dena ho toh PhonePe khulta hai naturally. | M5: In-depth (15+ min) | N5: Owner | O5: Paytm Soundbox | P5: Owner's personal phone | Q5: 300000 | R5: Distributor / wholesaler (stock) | S5: 4 | T5: 40000 | U5: PhonePe | V5: Staff salary | W5: 1 | X5: 12000 | Y5: Cash | AD5: Habit: other app is default | AE5: No | AF5: 5 | AG5: Yes | AH5: Yes | AI5: =IF(AND(U5<>"",U5<>"Cash",U5<>"Bank transfer (NEFT/RTGS)"),N(S5)*N(T5),0)+IF(AND(Y5<>"",Y5<>"Cash",Y5<>"Bank transfer (NEFT/RTGS)"),N(W5)*N(X5),0)+IF(AND(AC5<>"",AC5<>"Cash",AC5<>"Bank transfer (NEFT/RTGS)"),N(AA5)*N(AB5),0) -> 160000 | AJ5: =IF(U5="Paytm",N(S5)*N(T5),0)+IF(Y5="Paytm",N(W5)*N(X5),0)+IF(AC5="Paytm",N(AA5)*N(AB5),0) -> 0 | AK5: =IF(AI5>0,AJ5/AI5,"") -> 0 | AL5: =IF(AND(LEFT(O5,5)="Paytm",(N(S5)*N(T5)+N(W5)*N(X5)+N(AA5)*N(AB5))>0,AJ5<0.5*(N(S5)*N(T5)+N(W5)*N(X5)+N(AA5)*N(AB5))),1,0) -> 1
A6: VOC-002 | B6: 46289 | C6: Merchant | D6: IITK Shopping Complex | E6: Pharmacy / chemist | F6: Google Pay for stock bills; Bank transfer (NEFT/RTGS) for rent | G6: Google Pay | H6: Medical distributor apna GPay ka QR bhejta hai WhatsApp pe, wahi aasan hai. | I6: Customers pay on Paytm QR only; receiving only, no supplier payment goes through Paytm. Knew Paytm can pay suppliers but still uses other apps. | J6: Salesman shows his own QR | K6: Distributor-led onboarding: supplier's bill/QR lands in Chukta, salesman asks shop to pay there; keen on pay-later | L6: Medical distributor apna GPay ka QR bhejta hai WhatsApp pe, wahi aasan hai. | M6: In-depth (15+ min) | N6: Owner | O6: Paytm QR only | P6: Owner's personal phone | Q6: 500000 | R6: Distributor / wholesaler (stock) | S6: 8 | T6: 45000 | U6: Google Pay | V6: Shop rent | W6: 1 | X6: 15000 | Y6: Bank transfer (NEFT/RTGS) | AD6: Supplier shared another app's QR / asked | AE6: Yes | AF6: 4 | AG6: Yes | AH6: Not yet | AI6: =IF(AND(U6<>"",U6<>"Cash",U6<>"Bank transfer (NEFT/RTGS)"),N(S6)*N(T6),0)+IF(AND(Y6<>"",Y6<>"Cash",Y6<>"Bank transfer (NEFT/RTGS)"),N(W6)*N(X6),0)+IF(AND(AC6<>"",AC6<>"Cash",AC6<>"Bank transfer (NEFT/RTGS)"),N(AA6)*N(AB6),0) -> 360000 | AJ6: =IF(U6="Paytm",N(S6)*N(T6),0)+IF(Y6="Paytm",N(W6)*N(X6),0)+IF(AC6="Paytm",N(AA6)*N(AB6),0) -> 0 | AK6: =IF(AI6>0,AJ6/AI6,"") -> 0 | AL6: =IF(AND(LEFT(O6,5)="Paytm",(N(S6)*N(T6)+N(W6)*N(X6)+N(AA6)*N(AB6))>0,AJ6<0.5*(N(S6)*N(T6)+N(W6)*N(X6)+N(AA6)*N(AB6))),1,0) -> 1
A7: VOC-003 | B7: 46289 | C7: Merchant | D7: Hall 1 Canteen | E7: Restaurant / dhaba / canteen | F7: Cash for daily perishables; PhonePe for daily perishables | G7: PhonePe | H7: Sabji wala cash mangta hai aur baki ke liye PhonePe use karte hain. | I7: Customers pay on Paytm Soundbox; receiving only, no supplier payment goes through Paytm. Did not know Paytm can pay suppliers. | J7: Short on cash when stock arrives | K7: 7-day pay-later at stock time; supplier still paid instantly | L7: Sabji wala cash mangta hai aur baki ke liye PhonePe use karte hain. | M7: In-depth (15+ min) | O7: Paytm Soundbox | P7: Mostly cash / cheque | Q7: 150000 | R7: Daily perishables (milk, bread, veg) | S7: 30 | T7: 2000 | U7: Cash | V7: Daily perishables (milk, bread, veg) | W7: 30 | X7: 1500 | Y7: PhonePe | AD7: Short on cash when stock arrives | AE7: No | AF7: 4 | AG7: Yes | AH7: Yes | AI7: =IF(AND(U7<>"",U7<>"Cash",U7<>"Bank transfer (NEFT/RTGS)"),N(S7)*N(T7),0)+IF(AND(Y7<>"",Y7<>"Cash",Y7<>"Bank transfer (NEFT/RTGS)"),N(W7)*N(X7),0)+IF(AND(AC7<>"",AC7<>"Cash",AC7<>"Bank transfer (NEFT/RTGS)"),N(AA7)*N(AB7),0) -> 45000 | AJ7: =IF(U7="Paytm",N(S7)*N(T7),0)+IF(Y7="Paytm",N(W7)*N(X7),0)+IF(AC7="Paytm",N(AA7)*N(AB7),0) -> 0 | AK7: =IF(AI7>0,AJ7/AI7,"") -> 0 | AL7: =IF(AND(LEFT(O7,5)="Paytm",(N(S7)*N(T7)+N(W7)*N(X7)+N(AA7)*N(AB7))>0,AJ7<0.5*(N(S7)*N(T7)+N(W7)*N(X7)+N(AA7)*N(AB7))),1,0) -> 1
A8: VOC-004 | B8: 46289 | C8: Merchant | D8: Nankari | E8: Dairy / bakery / sweets | F8: PhonePe for stock bills; Google Pay for daily perishables | G8: PhonePe | H8: Dono kaam PhonePe se ho jate hain toh Paytm kyu rakhu. | I8: Customers pay on PhonePe Smartspeaker / QR; Paytm not used for receiving or paying suppliers. Did not know Paytm can pay suppliers. | J8: Habit: other app is default | K8: Put the supplier bill inside Paytm + Soundbox reminder so Paytm becomes the default place to pay | L8: Dono kaam PhonePe se ho jate hain toh Paytm kyu rakhu. | M8: In-depth (15+ min) | N8: Owner | O8: PhonePe Smartspeaker / QR | P8: Owner's personal phone | Q8: 80000 | R8: Distributor / wholesaler (stock) | S8: 30 | T8: 2000 | U8: PhonePe | V8: Daily perishables (milk, bread, veg) | W8: 4 | X8: 5000 | Y8: Google Pay | AD8: Habit: other app is default | AE8: No | AF8: 3 | AG8: Maybe | AH8: No | AI8: =IF(AND(U8<>"",U8<>"Cash",U8<>"Bank transfer (NEFT/RTGS)"),N(S8)*N(T8),0)+IF(AND(Y8<>"",Y8<>"Cash",Y8<>"Bank transfer (NEFT/RTGS)"),N(W8)*N(X8),0)+IF(AND(AC8<>"",AC8<>"Cash",AC8<>"Bank transfer (NEFT/RTGS)"),N(AA8)*N(AB8),0) -> 80000 | AJ8: =IF(U8="Paytm",N(S8)*N(T8),0)+IF(Y8="Paytm",N(W8)*N(X8),0)+IF(AC8="Paytm",N(AA8)*N(AB8),0) -> 0 | AK8: =IF(AI8>0,AJ8/AI8,"") -> 0 | AL8: =IF(AND(LEFT(O8,5)="Paytm",(N(S8)*N(T8)+N(W8)*N(X8)+N(AA8)*N(AB8))>0,AJ8<0.5*(N(S8)*N(T8)+N(W8)*N(X8)+N(AA8)*N(AB8))),1,0) -> 0
A9: VOC-005 | B9: 46289 | C9: Merchant | D9: Kalyanpur | E9: General / FMCG store | F9: Google Pay for stock bills; PhonePe for rent | G9: Google Pay | H9: Paytm me feature hai kya supplier ko dene ka? Pata nahi tha. | I9: Customers pay on Paytm Soundbox; receiving only, no supplier payment goes through Paytm. Did not know Paytm can pay suppliers. | J9: Unaware of feature | K9: Awareness at the counter: Soundbox / app prompt that Paytm can pay suppliers; keen on pay-later | L9: Paytm me feature hai kya supplier ko dene ka? Pata nahi tha. | M9: In-depth (15+ min) | O9: Paytm Soundbox | P9: Shop phone | Q9: 250000 | R9: Distributor / wholesaler (stock) | S9: 5 | T9: 30000 | U9: Google Pay | V9: Shop rent | W9: 1 | X9: 20000 | Y9: PhonePe | AD9: Didn't know Paytm can pay suppliers | AE9: No | AF9: 5 | AG9: Yes | AH9: Not yet | AI9: =IF(AND(U9<>"",U9<>"Cash",U9<>"Bank transfer (NEFT/RTGS)"),N(S9)*N(T9),0)+IF(AND(Y9<>"",Y9<>"Cash",Y9<>"Bank transfer (NEFT/RTGS)"),N(W9)*N(X9),0)+IF(AND(AC9<>"",AC9<>"Cash",AC9<>"Bank transfer (NEFT/RTGS)"),N(AA9)*N(AB9),0) -> 170000 | AJ9: =IF(U9="Paytm",N(S9)*N(T9),0)+IF(Y9="Paytm",N(W9)*N(X9),0)+IF(AC9="Paytm",N(AA9)*N(AB9),0) -> 0 | AK9: =IF(AI9>0,AJ9/AI9,"") -> 0 | AL9: =IF(AND(LEFT(O9,5)="Paytm",(N(S9)*N(T9)+N(W9)*N(X9)+N(AA9)*N(AB9))>0,AJ9<0.5*(N(S9)*N(T9)+N(W9)*N(X9)+N(AA9)*N(AB9))),1,0) -> 1
A10: VOC-006 | B10: 46289 | C10: Merchant | D10: MT Section | E10: Mobile / electronics | F10: Bank transfer (NEFT/RTGS) for stock bills; Cash for staff salary | G10: None (NEFT / cash only) | H10: Distributor direct account me transfer mangta hai NEFT se bade amount ke liye. | I10: Customers pay on Google Pay QR; Paytm not used for receiving or paying suppliers. Knew Paytm can pay suppliers but still uses other apps. | J10: High ticket sizes prefer NEFT | K10: Pay supplier's bank account over UPI (bills are under ₹1 L) with invoice attached; keen on pay-later | L10: Distributor direct account me transfer mangta hai NEFT se bade amount ke liye. | M10: In-depth (15+ min) | N10: Owner | O10: Google Pay QR | P10: Owner's personal phone | Q10: 400000 | R10: Distributor / wholesaler (stock) | S10: 3 | T10: 80000 | U10: Bank transfer (NEFT/RTGS) | V10: Staff salary | W10: 1 | X10: 15000 | Y10: Cash | AD10: Big bills go by NEFT / RTGS | AE10: Yes | AF10: 4 | AG10: Yes | AH10: Yes | AI10: =IF(AND(U10<>"",U10<>"Cash",U10<>"Bank transfer (NEFT/RTGS)"),N(S10)*N(T10),0)+IF(AND(Y10<>"",Y10<>"Cash",Y10<>"Bank transfer (NEFT/RTGS)"),N(W10)*N(X10),0)+IF(AND(AC10<>"",AC10<>"Cash",AC10<>"Bank transfer (NEFT/RTGS)"),N(AA10)*N(AB10),0) -> 0 | AJ10: =IF(U10="Paytm",N(S10)*N(T10),0)+IF(Y10="Paytm",N(W10)*N(X10),0)+IF(AC10="Paytm",N(AA10)*N(AB10),0) -> 0 | AK10: =IF(AI10>0,AJ10/AI10,"") | AL10: =IF(AND(LEFT(O10,5)="Paytm",(N(S10)*N(T10)+N(W10)*N(X10)+N(AA10)*N(AB10))>0,AJ10<0.5*(N(S10)*N(T10)+N(W10)*N(X10)+N(AA10)*N(AB10))),1,0) -> 0
A11: VOC-007 | B11: 46289 | C11: Merchant | D11: Hall 5 Canteen | E11: Restaurant / dhaba / canteen | F11: Cash for daily perishables; PhonePe for stock bills | G11: PhonePe | I11: Customers pay on Paytm Soundbox; receiving only, no supplier payment goes through Paytm. Did not know Paytm can pay suppliers. | J11: Staff manages cash drawer | K11: Give staff a controlled way to pay suppliers from the shop's Paytm, with a nightly summary for the owner | L11: Raat ko hisaab karna padta hai, ladka cash ginta hai. | M11: In-depth (15+ min) | O11: Paytm Soundbox | P11: Staff pays | Q11: 200000 | R11: Daily perishables (milk, bread, veg) | S11: 30 | T11: 3000 | U11: Cash | V11: Distributor / wholesaler (stock) | W11: 4 | X11: 25000 | Y11: PhonePe | AD11: Other | AE11: No | AF11: 4 | AG11: Maybe | AH11: Yes | AI11: =IF(AND(U11<>"",U11<>"Cash",U11<>"Bank transfer (NEFT/RTGS)"),N(S11)*N(T11),0)+IF(AND(Y11<>"",Y11<>"Cash",Y11<>"Bank transfer (NEFT/RTGS)"),N(W11)*N(X11),0)+IF(AND(AC11<>"",AC11<>"Cash",AC11<>"Bank transfer (NEFT/RTGS)"),N(AA11)*N(AB11),0) -> 100000 | AJ11: =IF(U11="Paytm",N(S11)*N(T11),0)+IF(Y11="Paytm",N(W11)*N(X11),0)+IF(AC11="Paytm",N(AA11)*N(AB11),0) -> 0 | AK11: =IF(AI11>0,AJ11/AI11,"") -> 0 | AL11: =IF(AND(LEFT(O11,5)="Paytm",(N(S11)*N(T11)+N(W11)*N(X11)+N(AA11)*N(AB11))>0,AJ11<0.5*(N(S11)*N(T11)+N(W11)*N(X11)+N(AA11)*N(AB11))),1,0) -> 1
A12: VOC-008 | B12: 46289 | C12: Merchant | D12: Kakadeo | E12: Stationery / books | F12: Google Pay for stock bills; PhonePe for rent | G12: Google Pay | H12: Aadat ban gayi hai GPay ki pichle teen saal se. | I12: Customers pay on Paytm Soundbox; receiving only, no supplier payment goes through Paytm. Did not know Paytm can pay suppliers. | J12: Habit: other app is default | K12: Put the supplier bill inside Paytm + Soundbox reminder so Paytm becomes the default place to pay; keen on pay-later | L12: Aadat ban gayi hai GPay ki pichle teen saal se. | M12: In-depth (15+ min) | N12: Owner | O12: Paytm Soundbox | P12: Owner's personal phone | Q12: 100000 | R12: Distributor / wholesaler (stock) | S12: 2 | T12: 40000 | U12: Google Pay | V12: Shop rent | W12: 1 | X12: 12000 | Y12: PhonePe | AD12: Habit: other app is default | AE12: No | AF12: 5 | AG12: Yes | AH12: No | AI12: =IF(AND(U12<>"",U12<>"Cash",U12<>"Bank transfer (NEFT/RTGS)"),N(S12)*N(T12),0)+IF(AND(Y12<>"",Y12<>"Cash",Y12<>"Bank transfer (NEFT/RTGS)"),N(W12)*N(X12),0)+IF(AND(AC12<>"",AC12<>"Cash",AC12<>"Bank transfer (NEFT/RTGS)"),N(AA12)*N(AB12),0) -> 92000 | AJ12: =IF(U12="Paytm",N(S12)*N(T12),0)+IF(Y12="Paytm",N(W12)*N(X12),0)+IF(AC12="Paytm",N(AA12)*N(AB12),0) -> 0 | AK12: =IF(AI12>0,AJ12/AI12,"") -> 0 | AL12: =IF(AND(LEFT(O12,5)="Paytm",(N(S12)*N(T12)+N(W12)*N(X12)+N(AA12)*N(AB12))>0,AJ12<0.5*(N(S12)*N(T12)+N(W12)*N(X12)+N(AA12)*N(AB12))),1,0) -> 1
A13: VOC-009 | B13: 46289 | C13: Merchant | D13: Kalyanpur | E13: Hardware / paint / sanitary | F13: Bank transfer (NEFT/RTGS) for stock bills; PhonePe for stock bills | G13: PhonePe | H13: GST bill hota hai toh bank se karte hain, baki salesman aake QR deta hai. | I13: Customers pay on Bank / other QR; Paytm not used for receiving or paying suppliers. Knew Paytm can pay suppliers but still uses other apps. | J13: Salesman shows his own QR | K13: Distributor-led onboarding: supplier's bill/QR lands in Chukta, salesman asks shop to pay there | L13: GST bill hota hai toh bank se karte hain, baki salesman aake QR deta hai. | M13: In-depth (15+ min) | N13: Owner | O13: Bank / other QR | P13: Owner's personal phone | Q13: 350000 | R13: Distributor / wholesaler (stock) | S13: 4 | T13: 50000 | U13: Bank transfer (NEFT/RTGS) | V13: Distributor / wholesaler (stock) | W13: 2 | X13: 75000 | Y13: PhonePe | AD13: Supplier shared another app's QR / asked | AE13: Yes | AF13: 3 | AG13: Maybe | AH13: Yes | AI13: =IF(AND(U13<>"",U13<>"Cash",U13<>"Bank transfer (NEFT/RTGS)"),N(S13)*N(T13),0)+IF(AND(Y13<>"",Y13<>"Cash",Y13<>"Bank transfer (NEFT/RTGS)"),N(W13)*N(X13),0)+IF(AND(AC13<>"",AC13<>"Cash",AC13<>"Bank transfer (NEFT/RTGS)"),N(AA13)*N(AB13),0) -> 150000 | AJ13: =IF(U13="Paytm",N(S13)*N(T13),0)+IF(Y13="Paytm",N(W13)*N(X13),0)+IF(AC13="Paytm",N(AA13)*N(AB13),0) -> 0 | AK13: =IF(AI13>0,AJ13/AI13,"") -> 0 | AL13: =IF(AND(LEFT(O13,5)="Paytm",(N(S13)*N(T13)+N(W13)*N(X13)+N(AA13)*N(AB13))>0,AJ13<0.5*(N(S13)*N(T13)+N(W13)*N(X13)+N(AA13)*N(AB13))),1,0) -> 0
A14: VOC-010 | B14: 46289 | C14: Merchant | D14: IITK Shopping Complex | E14: Clothing / footwear | F14: PhonePe for stock bills; Cash for staff salary | G14: PhonePe | I14: Customers pay on Paytm Soundbox; receiving only, no supplier payment goes through Paytm. Did not know Paytm can pay suppliers. | J14: App segregation | K14: Make paying as easy as receiving inside Paytm for Business, on the same phone; keen on pay-later | L14: Dukaan ke phone me bas Soundbox hai, payment mere private phone se hoti hai. | M14: In-depth (15+ min) | N14: Owner | O14: Paytm Soundbox | P14: Owner's personal phone | Q14: 200000 | R14: Distributor / wholesaler (stock) | S14: 2 | T14: 60000 | U14: PhonePe | V14: Staff salary | W14: 1 | X14: 10000 | Y14: Cash | AD14: Pays from personal phone (Paytm Business is only for receiving) | AE14: No | AF14: 5 | AG14: Yes | AH14: Not yet | AI14: =IF(AND(U14<>"",U14<>"Cash",U14<>"Bank transfer (NEFT/RTGS)"),N(S14)*N(T14),0)+IF(AND(Y14<>"",Y14<>"Cash",Y14<>"Bank transfer (NEFT/RTGS)"),N(W14)*N(X14),0)+IF(AND(AC14<>"",AC14<>"Cash",AC14<>"Bank transfer (NEFT/RTGS)"),N(AA14)*N(AB14),0) -> 120000 | AJ14: =IF(U14="Paytm",N(S14)*N(T14),0)+IF(Y14="Paytm",N(W14)*N(X14),0)+IF(AC14="Paytm",N(AA14)*N(AB14),0) -> 0 | AK14: =IF(AI14>0,AJ14/AI14,"") -> 0 | AL14: =IF(AND(LEFT(O14,5)="Paytm",(N(S14)*N(T14)+N(W14)*N(X14)+N(AA14)*N(AB14))>0,AJ14<0.5*(N(S14)*N(T14)+N(W14)*N(X14)+N(AA14)*N(AB14))),1,0) -> 1
A15: VOC-011 | B15: 46289 | C15: Merchant | D15: Nankari | E15: Kirana / grocery | F15: PhonePe for stock bills; Google Pay for daily perishables | G15: PhonePe | H15: PhonePe hi chalta hai, salesman wahi QR deta hai. | I15: Customers pay on Paytm QR only; receiving only, no supplier payment goes through Paytm. Did not know Paytm can pay suppliers. | J15: Salesman shows his own QR | K15: Distributor-led onboarding: supplier's bill/QR lands in Chukta, salesman asks shop to pay there | L15: PhonePe hi chalta hai, salesman wahi QR deta hai. | M15: Short (5 min) | N15: Owner | O15: Paytm QR only | P15: Owner's personal phone | Q15: 150000 | R15: Distributor / wholesaler (stock) | S15: 6 | T15: 15000 | U15: PhonePe | V15: Daily perishables (milk, bread, veg) | W15: 30 | X15: 800 | Y15: Google Pay | AD15: Supplier shared another app's QR / asked | AE15: No | AF15: 4 | AG15: Maybe | AH15: No | AI15: =IF(AND(U15<>"",U15<>"Cash",U15<>"Bank transfer (NEFT/RTGS)"),N(S15)*N(T15),0)+IF(AND(Y15<>"",Y15<>"Cash",Y15<>"Bank transfer (NEFT/RTGS)"),N(W15)*N(X15),0)+IF(AND(AC15<>"",AC15<>"Cash",AC15<>"Bank transfer (NEFT/RTGS)"),N(AA15)*N(AB15),0) -> 114000 | AJ15: =IF(U15="Paytm",N(S15)*N(T15),0)+IF(Y15="Paytm",N(W15)*N(X15),0)+IF(AC15="Paytm",N(AA15)*N(AB15),0) -> 0 | AK15: =IF(AI15>0,AJ15/AI15,"") -> 0 | AL15: =IF(AND(LEFT(O15,5)="Paytm",(N(S15)*N(T15)+N(W15)*N(X15)+N(AA15)*N(AB15))>0,AJ15<0.5*(N(S15)*N(T15)+N(W15)*N(X15)+N(AA15)*N(AB15))),1,0) -> 1
A16: VOC-012 | B16: 46289 | C16: Merchant | D16: Hall 2 Canteen | E16: Restaurant / dhaba / canteen | F16: Cash for daily perishables; PhonePe for stock bills | G16: PhonePe | I16: Customers pay on Paytm Soundbox; receiving only, no supplier payment goes through Paytm. Did not know Paytm can pay suppliers. | J16: Short on cash when stock arrives | K16: 7-day pay-later at stock time; supplier still paid instantly | L16: Cash nikalna padta hai ATM se sabji wale ke liye. | M16: Short (5 min) | O16: Paytm Soundbox | P16: Mostly cash / cheque | Q16: 120000 | R16: Daily perishables (milk, bread, veg) | S16: 30 | T16: 2500 | U16: Cash | V16: Distributor / wholesaler (stock) | W16: 4 | X16: 10000 | Y16: PhonePe | AD16: Short on cash when stock arrives | AE16: No | AF16: 5 | AG16: Yes | AH16: Yes | AI16: =IF(AND(U16<>"",U16<>"Cash",U16<>"Bank transfer (NEFT/RTGS)"),N(S16)*N(T16),0)+IF(AND(Y16<>"",Y16<>"Cash",Y16<>"Bank transfer (NEFT/RTGS)"),N(W16)*N(X16),0)+IF(AND(AC16<>"",AC16<>"Cash",AC16<>"Bank transfer (NEFT/RTGS)"),N(AA16)*N(AB16),0) -> 40000 | AJ16: =IF(U16="Paytm",N(S16)*N(T16),0)+IF(Y16="Paytm",N(W16)*N(X16),0)+IF(AC16="Paytm",N(AA16)*N(AB16),0) -> 0 | AK16: =IF(AI16>0,AJ16/AI16,"") -> 0 | AL16: =IF(AND(LEFT(O16,5)="Paytm",(N(S16)*N(T16)+N(W16)*N(X16)+N(AA16)*N(AB16))>0,AJ16<0.5*(N(S16)*N(T16)+N(W16)*N(X16)+N(AA16)*N(AB16))),1,0) -> 1
A17: VOC-013 | B17: 46289 | C17: Merchant | D17: Kalyanpur | E17: Pharmacy / chemist | F17: Google Pay for stock bills; Cash for staff salary | G17: Google Pay | H17: Scan karke pay karne me GPay aage hai. | I17: Customers pay on Google Pay QR; Paytm not used for receiving or paying suppliers. Did not know Paytm can pay suppliers. | J17: Habit: other app is default | K17: Put the supplier bill inside Paytm + Soundbox reminder so Paytm becomes the default place to pay; keen on pay-later | L17: Scan karke pay karne me GPay aage hai. | M17: Short (5 min) | N17: Owner | O17: Google Pay QR | P17: Owner's personal phone | Q17: 400000 | R17: Distributor / wholesaler (stock) | S17: 10 | T17: 30000 | U17: Google Pay | V17: Staff salary | W17: 1 | X17: 14000 | Y17: Cash | AD17: Habit: other app is default | AE17: No | AF17: 4 | AG17: Yes | AH17: Not yet | AI17: =IF(AND(U17<>"",U17<>"Cash",U17<>"Bank transfer (NEFT/RTGS)"),N(S17)*N(T17),0)+IF(AND(Y17<>"",Y17<>"Cash",Y17<>"Bank transfer (NEFT/RTGS)"),N(W17)*N(X17),0)+IF(AND(AC17<>"",AC17<>"Cash",AC17<>"Bank transfer (NEFT/RTGS)"),N(AA17)*N(AB17),0) -> 300000 | AJ17: =IF(U17="Paytm",N(S17)*N(T17),0)+IF(Y17="Paytm",N(W17)*N(X17),0)+IF(AC17="Paytm",N(AA17)*N(AB17),0) -> 0 | AK17: =IF(AI17>0,AJ17/AI17,"") -> 0 | AL17: =IF(AND(LEFT(O17,5)="Paytm",(N(S17)*N(T17)+N(W17)*N(X17)+N(AA17)*N(AB17))>0,AJ17<0.5*(N(S17)*N(T17)+N(W17)*N(X17)+N(AA17)*N(AB17))),1,0) -> 0
A18: VOC-014 | B18: 46289 | C18: Merchant | D18: Gurdev Palace | E18: General / FMCG store | F18: PhonePe for stock bills; Bank transfer (NEFT/RTGS) for rent | G18: PhonePe | H18: Hisaab alag alag jagah faila hua hai, PhonePe par history aasan hai. | I18: Customers pay on Paytm Soundbox; receiving only, no supplier payment goes through Paytm. Knew Paytm can pay suppliers but still uses other apps. | J18: Ledger reconciliation | K18: Invoice-tagged payments + auto purchase register; keen on pay-later | L18: Hisaab alag alag jagah faila hua hai, PhonePe par history aasan hai. | M18: Short (5 min) | N18: Owner | O18: Paytm Soundbox | P18: Owner's personal phone | Q18: 180000 | R18: Distributor / wholesaler (stock) | S18: 5 | T18: 25000 | U18: PhonePe | V18: Shop rent | W18: 1 | X18: 15000 | Y18: Bank transfer (NEFT/RTGS) | AD18: Hard to track which bill is paid | AE18: Yes | AF18: 5 | AG18: Yes | AH18: No | AI18: =IF(AND(U18<>"",U18<>"Cash",U18<>"Bank transfer (NEFT/RTGS)"),N(S18)*N(T18),0)+IF(AND(Y18<>"",Y18<>"Cash",Y18<>"Bank transfer (NEFT/RTGS)"),N(W18)*N(X18),0)+IF(AND(AC18<>"",AC18<>"Cash",AC18<>"Bank transfer (NEFT/RTGS)"),N(AA18)*N(AB18),0) -> 125000 | AJ18: =IF(U18="Paytm",N(S18)*N(T18),0)+IF(Y18="Paytm",N(W18)*N(X18),0)+IF(AC18="Paytm",N(AA18)*N(AB18),0) -> 0 | AK18: =IF(AI18>0,AJ18/AI18,"") -> 0 | AL18: =IF(AND(LEFT(O18,5)="Paytm",(N(S18)*N(T18)+N(W18)*N(X18)+N(AA18)*N(AB18))>0,AJ18<0.5*(N(S18)*N(T18)+N(W18)*N(X18)+N(AA18)*N(AB18))),1,0) -> 1
A19: VOC-015 | B19: 46289 | C19: Merchant | D19: Hall 12 Canteen | E19: Restaurant / dhaba / canteen | F19: PhonePe for daily perishables; Google Pay for stock bills | G19: PhonePe | H19: Ek hi app me sab ho jaye toh badhiya hai. | I19: Customers pay on Paytm QR only; receiving only, no supplier payment goes through Paytm. Did not know Paytm can pay suppliers. | J19: Habit: other app is default | K19: Put the supplier bill inside Paytm + Soundbox reminder so Paytm becomes the default place to pay | L19: Ek hi app me sab ho jaye toh badhiya hai. | M19: Short (5 min) | O19: Paytm QR only | P19: Shop phone | Q19: 90000 | R19: Daily perishables (milk, bread, veg) | S19: 30 | T19: 1500 | U19: PhonePe | V19: Distributor / wholesaler (stock) | W19: 2 | X19: 20000 | Y19: Google Pay | AD19: Habit: other app is default | AE19: No | AF19: 4 | AG19: Maybe | AH19: Not yet | AI19: =IF(AND(U19<>"",U19<>"Cash",U19<>"Bank transfer (NEFT/RTGS)"),N(S19)*N(T19),0)+IF(AND(Y19<>"",Y19<>"Cash",Y19<>"Bank transfer (NEFT/RTGS)"),N(W19)*N(X19),0)+IF(AND(AC19<>"",AC19<>"Cash",AC19<>"Bank transfer (NEFT/RTGS)"),N(AA19)*N(AB19),0) -> 85000 | AJ19: =IF(U19="Paytm",N(S19)*N(T19),0)+IF(Y19="Paytm",N(W19)*N(X19),0)+IF(AC19="Paytm",N(AA19)*N(AB19),0) -> 0 | AK19: =IF(AI19>0,AJ19/AI19,"") -> 0 | AL19: =IF(AND(LEFT(O19,5)="Paytm",(N(S19)*N(T19)+N(W19)*N(X19)+N(AA19)*N(AB19))>0,AJ19<0.5*(N(S19)*N(T19)+N(W19)*N(X19)+N(AA19)*N(AB19))),1,0) -> 1
A20: VOC-016 | B20: 46289 | C20: Merchant | D20: Kakadeo | E20: Kirana / grocery | F20: PhonePe for stock bills; Cash for rent | G20: PhonePe | H20: GPay par salesman ka QR scanned rehta hai, wahi use karta hu. | I20: Customers pay on Paytm Soundbox; receiving only, no supplier payment goes through Paytm. Did not know Paytm can pay suppliers. | J20: Salesman shows his own QR | K20: Distributor-led onboarding: supplier's bill/QR lands in Chukta, salesman asks shop to pay there; keen on pay-later | L20: GPay par salesman ka QR scanned rehta hai, wahi use karta hu. | M20: Short (5 min) | N20: Owner | O20: Paytm Soundbox | P20: Owner's personal phone | Q20: 220000 | R20: Distributor / wholesaler (stock) | S20: 8 | T20: 20000 | U20: PhonePe | V20: Shop rent | W20: 1 | X20: 18000 | Y20: Cash | AD20: Supplier shared another app's QR / asked | AE20: No | AF20: 5 | AG20: Yes | AH20: Yes | AI20: =IF(AND(U20<>"",U20<>"Cash",U20<>"Bank transfer (NEFT/RTGS)"),N(S20)*N(T20),0)+IF(AND(Y20<>"",Y20<>"Cash",Y20<>"Bank transfer (NEFT/RTGS)"),N(W20)*N(X20),0)+IF(AND(AC20<>"",AC20<>"Cash",AC20<>"Bank transfer (NEFT/RTGS)"),N(AA20)*N(AB20),0) -> 160000 | AJ20: =IF(U20="Paytm",N(S20)*N(T20),0)+IF(Y20="Paytm",N(W20)*N(X20),0)+IF(AC20="Paytm",N(AA20)*N(AB20),0) -> 0 | AK20: =IF(AI20>0,AJ20/AI20,"") -> 0 | AL20: =IF(AND(LEFT(O20,5)="Paytm",(N(S20)*N(T20)+N(W20)*N(X20)+N(AA20)*N(AB20))>0,AJ20<0.5*(N(S20)*N(T20)+N(W20)*N(X20)+N(AA20)*N(AB20))),1,0) -> 1
A21: VOC-017 | B21: 46289 | C21: Merchant | D21: Nankari | E21: Dairy / bakery / sweets | F21: Cash for stock bills; PhonePe for rent | G21: PhonePe | H21: Doodh wala cash ya PhonePe mangta hai daily. | I21: Customers pay on PhonePe Smartspeaker / QR; Paytm not used for receiving or paying suppliers. Did not know Paytm can pay suppliers. | J21: Habit: other app is default | K21: Put the supplier bill inside Paytm + Soundbox reminder so Paytm becomes the default place to pay | L21: Doodh wala cash ya PhonePe mangta hai daily. | M21: Short (5 min) | O21: PhonePe Smartspeaker / QR | P21: Staff pays | Q21: 70000 | R21: Distributor / wholesaler (stock) | S21: 30 | T21: 1500 | U21: Cash | V21: Shop rent | W21: 1 | X21: 10000 | Y21: PhonePe | AD21: Habit: other app is default | AE21: No | AF21: 3 | AG21: No | AH21: Yes | AI21: =IF(AND(U21<>"",U21<>"Cash",U21<>"Bank transfer (NEFT/RTGS)"),N(S21)*N(T21),0)+IF(AND(Y21<>"",Y21<>"Cash",Y21<>"Bank transfer (NEFT/RTGS)"),N(W21)*N(X21),0)+IF(AND(AC21<>"",AC21<>"Cash",AC21<>"Bank transfer (NEFT/RTGS)"),N(AA21)*N(AB21),0) -> 10000 | AJ21: =IF(U21="Paytm",N(S21)*N(T21),0)+IF(Y21="Paytm",N(W21)*N(X21),0)+IF(AC21="Paytm",N(AA21)*N(AB21),0) -> 0 | AK21: =IF(AI21>0,AJ21/AI21,"") -> 0 | AL21: =IF(AND(LEFT(O21,5)="Paytm",(N(S21)*N(T21)+N(W21)*N(X21)+N(AA21)*N(AB21))>0,AJ21<0.5*(N(S21)*N(T21)+N(W21)*N(X21)+N(AA21)*N(AB21))),1,0) -> 0
A22: VOC-018 | B22: 46289 | C22: Merchant | D22: IITK Shopping Complex | E22: Stationery / books | F22: Google Pay for stock bills; Cash for staff salary | G22: Google Pay | H22: Paytm business app kholna bhari lagta hai payment ke liye. | I22: Customers pay on Paytm Soundbox; receiving only, no supplier payment goes through Paytm. Did not know Paytm can pay suppliers. | J22: App segregation | K22: Make paying as easy as receiving inside Paytm for Business, on the same phone; keen on pay-later | L22: Paytm business app kholna bhari lagta hai payment ke liye. | M22: Short (5 min) | N22: Owner | O22: Paytm Soundbox | P22: Owner's personal phone | Q22: 80000 | R22: Distributor / wholesaler (stock) | S22: 2 | T22: 30000 | U22: Google Pay | V22: Staff salary | W22: 1 | X22: 8000 | Y22: Cash | AD22: Pays from personal phone (Paytm Business is only for receiving) | AE22: No | AF22: 4 | AG22: Yes | AH22: No | AI22: =IF(AND(U22<>"",U22<>"Cash",U22<>"Bank transfer (NEFT/RTGS)"),N(S22)*N(T22),0)+IF(AND(Y22<>"",Y22<>"Cash",Y22<>"Bank transfer (NEFT/RTGS)"),N(W22)*N(X22),0)+IF(AND(AC22<>"",AC22<>"Cash",AC22<>"Bank transfer (NEFT/RTGS)"),N(AA22)*N(AB22),0) -> 60000 | AJ22: =IF(U22="Paytm",N(S22)*N(T22),0)+IF(Y22="Paytm",N(W22)*N(X22),0)+IF(AC22="Paytm",N(AA22)*N(AB22),0) -> 0 | AK22: =IF(AI22>0,AJ22/AI22,"") -> 0 | AL22: =IF(AND(LEFT(O22,5)="Paytm",(N(S22)*N(T22)+N(W22)*N(X22)+N(AA22)*N(AB22))>0,AJ22<0.5*(N(S22)*N(T22)+N(W22)*N(X22)+N(AA22)*N(AB22))),1,0) -> 1
A23: VOC-019 | B23: 46289 | C23: Merchant | D23: Bithoor Road | E23: Hardware / paint / sanitary | F23: Bank transfer (NEFT/RTGS) for stock bills; PhonePe for stock bills | G23: PhonePe | H23: Bade payment bank transfer se hi safe lagte hain. | I23: Customers pay on Paytm QR only; receiving only, no supplier payment goes through Paytm. Knew Paytm can pay suppliers but still uses other apps. | J23: Trust/Large amounts | K23: Pay supplier's bank account over UPI (bills are under ₹1 L) with invoice attached | L23: Bade payment bank transfer se hi safe lagte hain. | M23: Short (5 min) | N23: Owner | O23: Paytm QR only | P23: Owner's personal phone | Q23: 280000 | R23: Distributor / wholesaler (stock) | S23: 4 | T23: 50000 | U23: Bank transfer (NEFT/RTGS) | V23: Distributor / wholesaler (stock) | W23: 4 | X23: 15000 | Y23: PhonePe | AD23: Big bills go by NEFT / RTGS | AE23: Yes | AF23: 3 | AG23: Maybe | AH23: Not yet | AI23: =IF(AND(U23<>"",U23<>"Cash",U23<>"Bank transfer (NEFT/RTGS)"),N(S23)*N(T23),0)+IF(AND(Y23<>"",Y23<>"Cash",Y23<>"Bank transfer (NEFT/RTGS)"),N(W23)*N(X23),0)+IF(AND(AC23<>"",AC23<>"Cash",AC23<>"Bank transfer (NEFT/RTGS)"),N(AA23)*N(AB23),0) -> 60000 | AJ23: =IF(U23="Paytm",N(S23)*N(T23),0)+IF(Y23="Paytm",N(W23)*N(X23),0)+IF(AC23="Paytm",N(AA23)*N(AB23),0) -> 0 | AK23: =IF(AI23>0,AJ23/AI23,"") -> 0 | AL23: =IF(AND(LEFT(O23,5)="Paytm",(N(S23)*N(T23)+N(W23)*N(X23)+N(AA23)*N(AB23))>0,AJ23<0.5*(N(S23)*N(T23)+N(W23)*N(X23)+N(AA23)*N(AB23))),1,0) -> 1
A24: VOC-020 | B24: 46289 | C24: Merchant | D24: Kalyanpur | E24: Kirana / grocery | F24: PhonePe for stock bills; Cash for daily perishables | G24: PhonePe | I24: Customers pay on Paytm Soundbox; receiving only, no supplier payment goes through Paytm. Did not know Paytm can pay suppliers. | J24: Short on cash when stock arrives | K24: 7-day pay-later at stock time; supplier still paid instantly | L24: Cash kam padta hai toh udhaar likhte hain copy me. | M24: Short (5 min) | O24: Paytm Soundbox | P24: Mostly cash / cheque | Q24: 180000 | R24: Distributor / wholesaler (stock) | S24: 6 | T24: 15000 | U24: PhonePe | V24: Daily perishables (milk, bread, veg) | W24: 30 | X24: 1000 | Y24: Cash | AD24: Short on cash when stock arrives | AE24: No | AF24: 5 | AG24: Yes | AH24: Yes | AI24: =IF(AND(U24<>"",U24<>"Cash",U24<>"Bank transfer (NEFT/RTGS)"),N(S24)*N(T24),0)+IF(AND(Y24<>"",Y24<>"Cash",Y24<>"Bank transfer (NEFT/RTGS)"),N(W24)*N(X24),0)+IF(AND(AC24<>"",AC24<>"Cash",AC24<>"Bank transfer (NEFT/RTGS)"),N(AA24)*N(AB24),0) -> 90000 | AJ24: =IF(U24="Paytm",N(S24)*N(T24),0)+IF(Y24="Paytm",N(W24)*N(X24),0)+IF(AC24="Paytm",N(AA24)*N(AB24),0) -> 0 | AK24: =IF(AI24>0,AJ24/AI24,"") -> 0 | AL24: =IF(AND(LEFT(O24,5)="Paytm",(N(S24)*N(T24)+N(W24)*N(X24)+N(AA24)*N(AB24))>0,AJ24<0.5*(N(S24)*N(T24)+N(W24)*N(X24)+N(AA24)*N(AB24))),1,0) -> 1
A25: VOC-021 | B25: 46289 | C25: Merchant | D25: Hall 13 Canteen | E25: Restaurant / dhaba / canteen | F25: Google Pay for daily perishables; PhonePe for stock bills | G25: Google Pay | H25: Canteen ka hisaab daily GPay se set ho jata hai. | I25: Customers pay on Paytm Soundbox; receiving only, no supplier payment goes through Paytm. Did not know Paytm can pay suppliers. | J25: Habit: other app is default | K25: Put the supplier bill inside Paytm + Soundbox reminder so Paytm becomes the default place to pay | L25: Canteen ka hisaab daily GPay se set ho jata hai. | M25: Short (5 min) | N25: Owner | O25: Paytm Soundbox | P25: Owner's personal phone | Q25: 140000 | R25: Daily perishables (milk, bread, veg) | S25: 30 | T25: 3000 | U25: Google Pay | V25: Distributor / wholesaler (stock) | W25: 2 | X25: 20000 | Y25: PhonePe | AD25: Habit: other app is default | AE25: No | AF25: 4 | AG25: Maybe | AH25: No | AI25: =IF(AND(U25<>"",U25<>"Cash",U25<>"Bank transfer (NEFT/RTGS)"),N(S25)*N(T25),0)+IF(AND(Y25<>"",Y25<>"Cash",Y25<>"Bank transfer (NEFT/RTGS)"),N(W25)*N(X25),0)+IF(AND(AC25<>"",AC25<>"Cash",AC25<>"Bank transfer (NEFT/RTGS)"),N(AA25)*N(AB25),0) -> 130000 | AJ25: =IF(U25="Paytm",N(S25)*N(T25),0)+IF(Y25="Paytm",N(W25)*N(X25),0)+IF(AC25="Paytm",N(AA25)*N(AB25),0) -> 0 | AK25: =IF(AI25>0,AJ25/AI25,"") -> 0 | AL25: =IF(AND(LEFT(O25,5)="Paytm",(N(S25)*N(T25)+N(W25)*N(X25)+N(AA25)*N(AB25))>0,AJ25<0.5*(N(S25)*N(T25)+N(W25)*N(X25)+N(AA25)*N(AB25))),1,0) -> 1
A26: VOC-022 | B26: 46289 | C26: Merchant | D26: MT Section | E26: Mobile / electronics | F26: Bank transfer (NEFT/RTGS) for stock bills; PhonePe for rent | G26: PhonePe | H26: Mobile accessories wali agency GPay par cash nahi leti bada, RTGS mangte hain. | I26: Customers pay on Paytm Soundbox; receiving only, no supplier payment goes through Paytm. Did not know Paytm can pay suppliers. | J26: High ticket sizes | K26: Pay supplier's bank account over UPI (bills are under ₹1 L) with invoice attached; keen on pay-later | L26: Mobile accessories wali agency GPay par cash nahi leti bada, RTGS mangte hain. | M26: Short (5 min) | N26: Owner | O26: Paytm Soundbox | P26: Owner's personal phone | Q26: 350000 | R26: Distributor / wholesaler (stock) | S26: 4 | T26: 70000 | U26: Bank transfer (NEFT/RTGS) | V26: Shop rent | W26: 1 | X26: 25000 | Y26: PhonePe | AD26: Big bills go by NEFT / RTGS | AE26: No | AF26: 4 | AG26: Yes | AH26: Yes | AI26: =IF(AND(U26<>"",U26<>"Cash",U26<>"Bank transfer (NEFT/RTGS)"),N(S26)*N(T26),0)+IF(AND(Y26<>"",Y26<>"Cash",Y26<>"Bank transfer (NEFT/RTGS)"),N(W26)*N(X26),0)+IF(AND(AC26<>"",AC26<>"Cash",AC26<>"Bank transfer (NEFT/RTGS)"),N(AA26)*N(AB26),0) -> 25000 | AJ26: =IF(U26="Paytm",N(S26)*N(T26),0)+IF(Y26="Paytm",N(W26)*N(X26),0)+IF(AC26="Paytm",N(AA26)*N(AB26),0) -> 0 | AK26: =IF(AI26>0,AJ26/AI26,"") -> 0 | AL26: =IF(AND(LEFT(O26,5)="Paytm",(N(S26)*N(T26)+N(W26)*N(X26)+N(AA26)*N(AB26))>0,AJ26<0.5*(N(S26)*N(T26)+N(W26)*N(X26)+N(AA26)*N(AB26))),1,0) -> 1
A27: VOC-023 | B27: 46289 | C27: Merchant | D27: Kakadeo | E27: Pharmacy / chemist | F27: Google Pay for stock bills; Cash for staff salary | G27: Google Pay | H27: Medical wale GPay prefer karte hain, wahi chalta aa raha hai. | I27: Customers pay on Paytm QR only; receiving only, no supplier payment goes through Paytm. Knew Paytm can pay suppliers but still uses other apps. | J27: Salesman shows his own QR | K27: Distributor-led onboarding: supplier's bill/QR lands in Chukta, salesman asks shop to pay there; keen on pay-later | L27: Medical wale GPay prefer karte hain, wahi chalta aa raha hai. | M27: Short (5 min) | N27: Owner | O27: Paytm QR only | P27: Owner's personal phone | Q27: 450000 | R27: Distributor / wholesaler (stock) | S27: 12 | T27: 30000 | U27: Google Pay | V27: Staff salary | W27: 1 | X27: 15000 | Y27: Cash | AD27: Supplier shared another app's QR / asked | AE27: Yes | AF27: 5 | AG27: Yes | AH27: Not yet | AI27: =IF(AND(U27<>"",U27<>"Cash",U27<>"Bank transfer (NEFT/RTGS)"),N(S27)*N(T27),0)+IF(AND(Y27<>"",Y27<>"Cash",Y27<>"Bank transfer (NEFT/RTGS)"),N(W27)*N(X27),0)+IF(AND(AC27<>"",AC27<>"Cash",AC27<>"Bank transfer (NEFT/RTGS)"),N(AA27)*N(AB27),0) -> 360000 | AJ27: =IF(U27="Paytm",N(S27)*N(T27),0)+IF(Y27="Paytm",N(W27)*N(X27),0)+IF(AC27="Paytm",N(AA27)*N(AB27),0) -> 0 | AK27: =IF(AI27>0,AJ27/AI27,"") -> 0 | AL27: =IF(AND(LEFT(O27,5)="Paytm",(N(S27)*N(T27)+N(W27)*N(X27)+N(AA27)*N(AB27))>0,AJ27<0.5*(N(S27)*N(T27)+N(W27)*N(X27)+N(AA27)*N(AB27))),1,0) -> 1
A28: VOC-024 | B28: 46289 | C28: Merchant | D28: Nankari | E28: General / FMCG store | F28: PhonePe for stock bills; Cash for rent | G28: PhonePe | H28: PhonePe sab use karte hain yahan gali me. | I28: Customers pay on PhonePe Smartspeaker / QR; Paytm not used for receiving or paying suppliers. Did not know Paytm can pay suppliers. | J28: Habit: other app is default | K28: Put the supplier bill inside Paytm + Soundbox reminder so Paytm becomes the default place to pay | L28: PhonePe sab use karte hain yahan gali me. | M28: Short (5 min) | N28: Owner | O28: PhonePe Smartspeaker / QR | P28: Owner's personal phone | Q28: 160000 | R28: Distributor / wholesaler (stock) | S28: 5 | T28: 20000 | U28: PhonePe | V28: Shop rent | W28: 1 | X28: 10000 | Y28: Cash | AD28: Habit: other app is default | AE28: No | AF28: 3 | AG28: Maybe | AH28: Yes | AI28: =IF(AND(U28<>"",U28<>"Cash",U28<>"Bank transfer (NEFT/RTGS)"),N(S28)*N(T28),0)+IF(AND(Y28<>"",Y28<>"Cash",Y28<>"Bank transfer (NEFT/RTGS)"),N(W28)*N(X28),0)+IF(AND(AC28<>"",AC28<>"Cash",AC28<>"Bank transfer (NEFT/RTGS)"),N(AA28)*N(AB28),0) -> 100000 | AJ28: =IF(U28="Paytm",N(S28)*N(T28),0)+IF(Y28="Paytm",N(W28)*N(X28),0)+IF(AC28="Paytm",N(AA28)*N(AB28),0) -> 0 | AK28: =IF(AI28>0,AJ28/AI28,"") -> 0 | AL28: =IF(AND(LEFT(O28,5)="Paytm",(N(S28)*N(T28)+N(W28)*N(X28)+N(AA28)*N(AB28))>0,AJ28<0.5*(N(S28)*N(T28)+N(W28)*N(X28)+N(AA28)*N(AB28))),1,0) -> 0
A29: VOC-025 | B29: 46289 | C29: Merchant | D29: IITK Shopping Complex | E29: Kirana / grocery | F29: Google Pay for stock bills; Bank transfer (NEFT/RTGS) for rent | G29: Google Pay | H29: Soundbox bolta hai toh trust hota hai, par pay karne ke liye PhonePe theek hai. | I29: Customers pay on Paytm Soundbox; receiving only, no supplier payment goes through Paytm. Did not know Paytm can pay suppliers. | J29: App segregation | K29: Make paying as easy as receiving inside Paytm for Business, on the same phone; keen on pay-later | L29: Soundbox bolta hai toh trust hota hai, par pay karne ke liye PhonePe theek hai. | M29: Short (5 min) | O29: Paytm Soundbox | P29: Shop phone | Q29: 280000 | R29: Distributor / wholesaler (stock) | S29: 8 | T29: 25000 | U29: Google Pay | V29: Shop rent | W29: 1 | X29: 15000 | Y29: Bank transfer (NEFT/RTGS) | AD29: Pays from personal phone (Paytm Business is only for receiving) | AE29: No | AF29: 5 | AG29: Yes | AH29: No | AI29: =IF(AND(U29<>"",U29<>"Cash",U29<>"Bank transfer (NEFT/RTGS)"),N(S29)*N(T29),0)+IF(AND(Y29<>"",Y29<>"Cash",Y29<>"Bank transfer (NEFT/RTGS)"),N(W29)*N(X29),0)+IF(AND(AC29<>"",AC29<>"Cash",AC29<>"Bank transfer (NEFT/RTGS)"),N(AA29)*N(AB29),0) -> 200000 | AJ29: =IF(U29="Paytm",N(S29)*N(T29),0)+IF(Y29="Paytm",N(W29)*N(X29),0)+IF(AC29="Paytm",N(AA29)*N(AB29),0) -> 0 | AK29: =IF(AI29>0,AJ29/AI29,"") -> 0 | AL29: =IF(AND(LEFT(O29,5)="Paytm",(N(S29)*N(T29)+N(W29)*N(X29)+N(AA29)*N(AB29))>0,AJ29<0.5*(N(S29)*N(T29)+N(W29)*N(X29)+N(AA29)*N(AB29))),1,0) -> 1
A30: VOC-026 | B30: 46289 | C30: Merchant | D30: Hall 5 Canteen | E30: Restaurant / dhaba / canteen | F30: Cash for daily perishables; PhonePe for daily perishables | G30: PhonePe | I30: Customers pay on Paytm Soundbox; receiving only, no supplier payment goes through Paytm. Did not know Paytm can pay suppliers. | J30: Short on cash when stock arrives | K30: 7-day pay-later at stock time; supplier still paid instantly | L30: Staff pay karta hai kabhi kabhi cash me subah subah. | M30: Short (5 min) | O30: Paytm Soundbox | P30: Staff pays | Q30: 180000 | R30: Daily perishables (milk, bread, veg) | S30: 30 | T30: 4000 | U30: Cash | V30: Daily perishables (milk, bread, veg) | W30: 30 | X30: 1500 | Y30: PhonePe | AD30: Short on cash when stock arrives | AE30: No | AF30: 4 | AG30: Yes | AH30: Yes | AI30: =IF(AND(U30<>"",U30<>"Cash",U30<>"Bank transfer (NEFT/RTGS)"),N(S30)*N(T30),0)+IF(AND(Y30<>"",Y30<>"Cash",Y30<>"Bank transfer (NEFT/RTGS)"),N(W30)*N(X30),0)+IF(AND(AC30<>"",AC30<>"Cash",AC30<>"Bank transfer (NEFT/RTGS)"),N(AA30)*N(AB30),0) -> 45000 | AJ30: =IF(U30="Paytm",N(S30)*N(T30),0)+IF(Y30="Paytm",N(W30)*N(X30),0)+IF(AC30="Paytm",N(AA30)*N(AB30),0) -> 0 | AK30: =IF(AI30>0,AJ30/AI30,"") -> 0 | AL30: =IF(AND(LEFT(O30,5)="Paytm",(N(S30)*N(T30)+N(W30)*N(X30)+N(AA30)*N(AB30))>0,AJ30<0.5*(N(S30)*N(T30)+N(W30)*N(X30)+N(AA30)*N(AB30))),1,0) -> 1
A31: VOC-027 | B31: 46289 | C31: Merchant | D31: Kalyanpur | E31: Clothing / footwear | F31: Bank transfer (NEFT/RTGS) for stock bills; PhonePe for rent | G31: PhonePe | H31: Kapde ka stock bada hota hai, RTGS se jata hai. | I31: Customers pay on Paytm Soundbox; receiving only, no supplier payment goes through Paytm. Knew Paytm can pay suppliers but still uses other apps. | J31: High ticket sizes | K31: Pay supplier's bank account over UPI (bills are under ₹1 L) with invoice attached; keen on pay-later | L31: Kapde ka stock bada hota hai, RTGS se jata hai. | M31: Short (5 min) | N31: Owner | O31: Paytm Soundbox | P31: Owner's personal phone | Q31: 250000 | R31: Distributor / wholesaler (stock) | S31: 3 | T31: 60000 | U31: Bank transfer (NEFT/RTGS) | V31: Shop rent | W31: 1 | X31: 20000 | Y31: PhonePe | AD31: Big bills go by NEFT / RTGS | AE31: Yes | AF31: 4 | AG31: Yes | AH31: Not yet | AI31: =IF(AND(U31<>"",U31<>"Cash",U31<>"Bank transfer (NEFT/RTGS)"),N(S31)*N(T31),0)+IF(AND(Y31<>"",Y31<>"Cash",Y31<>"Bank transfer (NEFT/RTGS)"),N(W31)*N(X31),0)+IF(AND(AC31<>"",AC31<>"Cash",AC31<>"Bank transfer (NEFT/RTGS)"),N(AA31)*N(AB31),0) -> 20000 | AJ31: =IF(U31="Paytm",N(S31)*N(T31),0)+IF(Y31="Paytm",N(W31)*N(X31),0)+IF(AC31="Paytm",N(AA31)*N(AB31),0) -> 0 | AK31: =IF(AI31>0,AJ31/AI31,"") -> 0 | AL31: =IF(AND(LEFT(O31,5)="Paytm",(N(S31)*N(T31)+N(W31)*N(X31)+N(AA31)*N(AB31))>0,AJ31<0.5*(N(S31)*N(T31)+N(W31)*N(X31)+N(AA31)*N(AB31))),1,0) -> 1
A32: VOC-028 | B32: 46289 | C32: Merchant | D32: Gurdev Palace | E32: Dairy / bakery / sweets | F32: Cash for stock bills; PhonePe for rent | G32: PhonePe | H32: Bread wala daily cash le jata hai, UPI nahi leta. | I32: Customers pay on Google Pay QR; Paytm not used for receiving or paying suppliers. Did not know Paytm can pay suppliers. | J32: Salesman shows his own QR | K32: Distributor-led onboarding: supplier's bill/QR lands in Chukta, salesman asks shop to pay there | L32: Bread wala daily cash le jata hai, UPI nahi leta. | M32: Short (5 min) | O32: Google Pay QR | P32: Mostly cash / cheque | Q32: 90000 | R32: Distributor / wholesaler (stock) | S32: 30 | T32: 2000 | U32: Cash | V32: Shop rent | W32: 1 | X32: 12000 | Y32: PhonePe | AD32: Supplier shared another app's QR / asked | AE32: No | AF32: 3 | AG32: No | AH32: Yes | AI32: =IF(AND(U32<>"",U32<>"Cash",U32<>"Bank transfer (NEFT/RTGS)"),N(S32)*N(T32),0)+IF(AND(Y32<>"",Y32<>"Cash",Y32<>"Bank transfer (NEFT/RTGS)"),N(W32)*N(X32),0)+IF(AND(AC32<>"",AC32<>"Cash",AC32<>"Bank transfer (NEFT/RTGS)"),N(AA32)*N(AB32),0) -> 12000 | AJ32: =IF(U32="Paytm",N(S32)*N(T32),0)+IF(Y32="Paytm",N(W32)*N(X32),0)+IF(AC32="Paytm",N(AA32)*N(AB32),0) -> 0 | AK32: =IF(AI32>0,AJ32/AI32,"") -> 0 | AL32: =IF(AND(LEFT(O32,5)="Paytm",(N(S32)*N(T32)+N(W32)*N(X32)+N(AA32)*N(AB32))>0,AJ32<0.5*(N(S32)*N(T32)+N(W32)*N(X32)+N(AA32)*N(AB32))),1,0) -> 0
A33: VOC-029 | B33: 46289 | C33: Merchant | D33: Kakadeo | E33: Kirana / grocery | F33: PhonePe for stock bills; Google Pay for daily perishables | G33: PhonePe | H33: App badalne me aalas aata hai yaar. | I33: Customers pay on Paytm Soundbox; receiving only, no supplier payment goes through Paytm. Did not know Paytm can pay suppliers. | J33: Habit: other app is default | K33: Put the supplier bill inside Paytm + Soundbox reminder so Paytm becomes the default place to pay | L33: App badalne me aalas aata hai yaar. | M33: Short (5 min) | N33: Owner | O33: Paytm Soundbox | P33: Owner's personal phone | Q33: 190000 | R33: Distributor / wholesaler (stock) | S33: 6 | T33: 20000 | U33: PhonePe | V33: Daily perishables (milk, bread, veg) | W33: 30 | X33: 1500 | Y33: Google Pay | AD33: Habit: other app is default | AE33: No | AF33: 4 | AG33: Maybe | AH33: No | AI33: =IF(AND(U33<>"",U33<>"Cash",U33<>"Bank transfer (NEFT/RTGS)"),N(S33)*N(T33),0)+IF(AND(Y33<>"",Y33<>"Cash",Y33<>"Bank transfer (NEFT/RTGS)"),N(W33)*N(X33),0)+IF(AND(AC33<>"",AC33<>"Cash",AC33<>"Bank transfer (NEFT/RTGS)"),N(AA33)*N(AB33),0) -> 165000 | AJ33: =IF(U33="Paytm",N(S33)*N(T33),0)+IF(Y33="Paytm",N(W33)*N(X33),0)+IF(AC33="Paytm",N(AA33)*N(AB33),0) -> 0 | AK33: =IF(AI33>0,AJ33/AI33,"") -> 0 | AL33: =IF(AND(LEFT(O33,5)="Paytm",(N(S33)*N(T33)+N(W33)*N(X33)+N(AA33)*N(AB33))>0,AJ33<0.5*(N(S33)*N(T33)+N(W33)*N(X33)+N(AA33)*N(AB33))),1,0) -> 1
A34: VOC-030 | B34: 46289 | C34: Merchant | D34: Nankari | E34: Pharmacy / chemist | F34: Google Pay for stock bills; PhonePe for staff salary | G34: Google Pay | H34: Challan WhatsApp pe aata hai, wahi se pay kar dete hain GPay pe. | I34: Customers pay on Paytm QR only; receiving only, no supplier payment goes through Paytm. Did not know Paytm can pay suppliers. | J34: Salesman shows his own QR | K34: Distributor-led onboarding: supplier's bill/QR lands in Chukta, salesman asks shop to pay there; keen on pay-later | L34: Challan WhatsApp pe aata hai, wahi se pay kar dete hain GPay pe. | M34: Short (5 min) | N34: Owner | O34: Paytm QR only | P34: Owner's personal phone | Q34: 350000 | R34: Distributor / wholesaler (stock) | S34: 10 | T34: 25000 | U34: Google Pay | V34: Staff salary | W34: 1 | X34: 12000 | Y34: PhonePe | AD34: Supplier shared another app's QR / asked | AE34: No | AF34: 5 | AG34: Yes | AH34: Not yet | AI34: =IF(AND(U34<>"",U34<>"Cash",U34<>"Bank transfer (NEFT/RTGS)"),N(S34)*N(T34),0)+IF(AND(Y34<>"",Y34<>"Cash",Y34<>"Bank transfer (NEFT/RTGS)"),N(W34)*N(X34),0)+IF(AND(AC34<>"",AC34<>"Cash",AC34<>"Bank transfer (NEFT/RTGS)"),N(AA34)*N(AB34),0) -> 262000 | AJ34: =IF(U34="Paytm",N(S34)*N(T34),0)+IF(Y34="Paytm",N(W34)*N(X34),0)+IF(AC34="Paytm",N(AA34)*N(AB34),0) -> 0 | AK34: =IF(AI34>0,AJ34/AI34,"") -> 0 | AL34: =IF(AND(LEFT(O34,5)="Paytm",(N(S34)*N(T34)+N(W34)*N(X34)+N(AA34)*N(AB34))>0,AJ34<0.5*(N(S34)*N(T34)+N(W34)*N(X34)+N(AA34)*N(AB34))),1,0) -> 1
A35: VOC-031 | B35: 46289 | C35: Merchant | D35: IITK Shopping Complex | E35: General / FMCG store | F35: PhonePe for stock bills; Bank transfer (NEFT/RTGS) for rent | G35: PhonePe | H35: Paytm se personal payment karte hain, business ke liye GPay. | I35: Customers pay on Paytm Soundbox; receiving only, no supplier payment goes through Paytm. Did not know Paytm can pay suppliers. | J35: Habit: other app is default | K35: Put the supplier bill inside Paytm + Soundbox reminder so Paytm becomes the default place to pay; keen on pay-later | L35: Paytm se personal payment karte hain, business ke liye GPay. | M35: Short (5 min) | O35: Paytm Soundbox | P35: Shop phone | Q35: 150000 | R35: Distributor / wholesaler (stock) | S35: 5 | T35: 20000 | U35: PhonePe | V35: Shop rent | W35: 1 | X35: 15000 | Y35: Bank transfer (NEFT/RTGS) | AD35: Habit: other app is default | AE35: No | AF35: 4 | AG35: Yes | AH35: No | AI35: =IF(AND(U35<>"",U35<>"Cash",U35<>"Bank transfer (NEFT/RTGS)"),N(S35)*N(T35),0)+IF(AND(Y35<>"",Y35<>"Cash",Y35<>"Bank transfer (NEFT/RTGS)"),N(W35)*N(X35),0)+IF(AND(AC35<>"",AC35<>"Cash",AC35<>"Bank transfer (NEFT/RTGS)"),N(AA35)*N(AB35),0) -> 100000 | AJ35: =IF(U35="Paytm",N(S35)*N(T35),0)+IF(Y35="Paytm",N(W35)*N(X35),0)+IF(AC35="Paytm",N(AA35)*N(AB35),0) -> 0 | AK35: =IF(AI35>0,AJ35/AI35,"") -> 0 | AL35: =IF(AND(LEFT(O35,5)="Paytm",(N(S35)*N(T35)+N(W35)*N(X35)+N(AA35)*N(AB35))>0,AJ35<0.5*(N(S35)*N(T35)+N(W35)*N(X35)+N(AA35)*N(AB35))),1,0) -> 1
A36: VOC-032 | B36: 46289 | C36: Merchant | D36: Hall 1 Canteen | E36: Restaurant / dhaba / canteen | F36: Cash for daily perishables; PhonePe for daily perishables | G36: PhonePe | H36: Bhaiya, udhaar toh chalta hi hai, Paytm 7 din dega toh badhiya hai. | I36: Customers pay on Paytm Soundbox; receiving only, no supplier payment goes through Paytm. Did not know Paytm can pay suppliers. | J36: Short on cash when stock arrives | K36: 7-day pay-later at stock time; supplier still paid instantly | L36: Bhaiya, udhaar toh chalta hi hai, Paytm 7 din dega toh badhiya hai. | M36: Short (5 min) | O36: Paytm Soundbox | P36: Mostly cash / cheque | Q36: 110000 | R36: Daily perishables (milk, bread, veg) | S36: 30 | T36: 2500 | U36: Cash | V36: Daily perishables (milk, bread, veg) | W36: 30 | X36: 1000 | Y36: PhonePe | AD36: Short on cash when stock arrives | AE36: No | AF36: 5 | AG36: Yes | AH36: Yes | AI36: =IF(AND(U36<>"",U36<>"Cash",U36<>"Bank transfer (NEFT/RTGS)"),N(S36)*N(T36),0)+IF(AND(Y36<>"",Y36<>"Cash",Y36<>"Bank transfer (NEFT/RTGS)"),N(W36)*N(X36),0)+IF(AND(AC36<>"",AC36<>"Cash",AC36<>"Bank transfer (NEFT/RTGS)"),N(AA36)*N(AB36),0) -> 30000 | AJ36: =IF(U36="Paytm",N(S36)*N(T36),0)+IF(Y36="Paytm",N(W36)*N(X36),0)+IF(AC36="Paytm",N(AA36)*N(AB36),0) -> 0 | AK36: =IF(AI36>0,AJ36/AI36,"") -> 0 | AL36: =IF(AND(LEFT(O36,5)="Paytm",(N(S36)*N(T36)+N(W36)*N(X36)+N(AA36)*N(AB36))>0,AJ36<0.5*(N(S36)*N(T36)+N(W36)*N(X36)+N(AA36)*N(AB36))),1,0) -> 1
A37: VOC-033 | B37: 46289 | C37: Merchant | D37: Kalyanpur | E37: Stationery / books | F37: Google Pay for stock bills; PhonePe for rent | G37: Google Pay | H37: Stationery ka stock mahine me ek baar aata hai, GPay se jata hai. | I37: Customers pay on PhonePe Smartspeaker / QR; Paytm not used for receiving or paying suppliers. Did not know Paytm can pay suppliers. | J37: Habit: other app is default | K37: Put the supplier bill inside Paytm + Soundbox reminder so Paytm becomes the default place to pay | L37: Stationery ka stock mahine me ek baar aata hai, GPay se jata hai. | M37: Short (5 min) | N37: Owner | O37: PhonePe Smartspeaker / QR | P37: Owner's personal phone | Q37: 70000 | R37: Distributor / wholesaler (stock) | S37: 2 | T37: 25000 | U37: Google Pay | V37: Shop rent | W37: 1 | X37: 10000 | Y37: PhonePe | AD37: Habit: other app is default | AE37: No | AF37: 4 | AG37: Maybe | AH37: No | AI37: =IF(AND(U37<>"",U37<>"Cash",U37<>"Bank transfer (NEFT/RTGS)"),N(S37)*N(T37),0)+IF(AND(Y37<>"",Y37<>"Cash",Y37<>"Bank transfer (NEFT/RTGS)"),N(W37)*N(X37),0)+IF(AND(AC37<>"",AC37<>"Cash",AC37<>"Bank transfer (NEFT/RTGS)"),N(AA37)*N(AB37),0) -> 60000 | AJ37: =IF(U37="Paytm",N(S37)*N(T37),0)+IF(Y37="Paytm",N(W37)*N(X37),0)+IF(AC37="Paytm",N(AA37)*N(AB37),0) -> 0 | AK37: =IF(AI37>0,AJ37/AI37,"") -> 0 | AL37: =IF(AND(LEFT(O37,5)="Paytm",(N(S37)*N(T37)+N(W37)*N(X37)+N(AA37)*N(AB37))>0,AJ37<0.5*(N(S37)*N(T37)+N(W37)*N(X37)+N(AA37)*N(AB37))),1,0) -> 0
A38: VOC-034 | B38: 46289 | C38: Merchant | D38: Bithoor Road | E38: Hardware / paint / sanitary | F38: Bank transfer (NEFT/RTGS) for stock bills; Cash for staff salary | G38: None (NEFT / cash only) | I38: Customers pay on Paytm Soundbox; receiving only, no supplier payment goes through Paytm. Knew Paytm can pay suppliers but still uses other apps. | J38: High ticket sizes | K38: Pay supplier's bank account over UPI (bills are under ₹1 L) with invoice attached | L38: Distributor bolta hai direct current account me daal do. | M38: Short (5 min) | N38: Owner | O38: Paytm Soundbox | P38: Owner's personal phone | Q38: 320000 | R38: Distributor / wholesaler (stock) | S38: 5 | T38: 40000 | U38: Bank transfer (NEFT/RTGS) | V38: Staff salary | W38: 1 | X38: 15000 | Y38: Cash | AD38: Big bills go by NEFT / RTGS | AE38: Yes | AF38: 3 | AG38: Maybe | AH38: Yes | AI38: =IF(AND(U38<>"",U38<>"Cash",U38<>"Bank transfer (NEFT/RTGS)"),N(S38)*N(T38),0)+IF(AND(Y38<>"",Y38<>"Cash",Y38<>"Bank transfer (NEFT/RTGS)"),N(W38)*N(X38),0)+IF(AND(AC38<>"",AC38<>"Cash",AC38<>"Bank transfer (NEFT/RTGS)"),N(AA38)*N(AB38),0) -> 0 | AJ38: =IF(U38="Paytm",N(S38)*N(T38),0)+IF(Y38="Paytm",N(W38)*N(X38),0)+IF(AC38="Paytm",N(AA38)*N(AB38),0) -> 0 | AK38: =IF(AI38>0,AJ38/AI38,"") | AL38: =IF(AND(LEFT(O38,5)="Paytm",(N(S38)*N(T38)+N(W38)*N(X38)+N(AA38)*N(AB38))>0,AJ38<0.5*(N(S38)*N(T38)+N(W38)*N(X38)+N(AA38)*N(AB38))),1,0) -> 1
A39: VOC-035 | B39: 46289 | C39: Merchant | D39: Kakadeo | E39: Mobile / electronics | F39: Google Pay for stock bills; PhonePe for rent | G39: Google Pay | H39: Kaam ke time jo app jaldi khule usse pay kar dete hain. | I39: Customers pay on Paytm QR only; receiving only, no supplier payment goes through Paytm. Did not know Paytm can pay suppliers. | J39: Habit: other app is default | K39: Put the supplier bill inside Paytm + Soundbox reminder so Paytm becomes the default place to pay; keen on pay-later | L39: Kaam ke time jo app jaldi khule usse pay kar dete hain. | M39: Short (5 min) | N39: Owner | O39: Paytm QR only | P39: Owner's personal phone | Q39: 250000 | R39: Distributor / wholesaler (stock) | S39: 4 | T39: 45000 | U39: Google Pay | V39: Shop rent | W39: 1 | X39: 18000 | Y39: PhonePe | AD39: Habit: other app is default | AE39: No | AF39: 4 | AG39: Yes | AH39: Not yet | AI39: =IF(AND(U39<>"",U39<>"Cash",U39<>"Bank transfer (NEFT/RTGS)"),N(S39)*N(T39),0)+IF(AND(Y39<>"",Y39<>"Cash",Y39<>"Bank transfer (NEFT/RTGS)"),N(W39)*N(X39),0)+IF(AND(AC39<>"",AC39<>"Cash",AC39<>"Bank transfer (NEFT/RTGS)"),N(AA39)*N(AB39),0) -> 198000 | AJ39: =IF(U39="Paytm",N(S39)*N(T39),0)+IF(Y39="Paytm",N(W39)*N(X39),0)+IF(AC39="Paytm",N(AA39)*N(AB39),0) -> 0 | AK39: =IF(AI39>0,AJ39/AI39,"") -> 0 | AL39: =IF(AND(LEFT(O39,5)="Paytm",(N(S39)*N(T39)+N(W39)*N(X39)+N(AA39)*N(AB39))>0,AJ39<0.5*(N(S39)*N(T39)+N(W39)*N(X39)+N(AA39)*N(AB39))),1,0) -> 1
A40: VOC-036 | B40: 46289 | C40: Merchant | D40: MT Section | E40: Kirana / grocery | F40: PhonePe for stock bills; Cash for daily perishables | G40: PhonePe | I40: Customers pay on Paytm Soundbox; receiving only, no supplier payment goes through Paytm. Did not know Paytm can pay suppliers. | J40: Short on cash when stock arrives | K40: 7-day pay-later at stock time; supplier still paid instantly | L40: Kal kya dena hai bata de toh tension kam hogi, yaad nahi rehta. | M40: Short (5 min) | O40: Paytm Soundbox | P40: Mostly cash / cheque | Q40: 200000 | R40: Distributor / wholesaler (stock) | S40: 6 | T40: 18000 | U40: PhonePe | V40: Daily perishables (milk, bread, veg) | W40: 30 | X40: 1500 | Y40: Cash | AD40: Short on cash when stock arrives | AE40: No | AF40: 5 | AG40: Yes | AH40: Yes | AI40: =IF(AND(U40<>"",U40<>"Cash",U40<>"Bank transfer (NEFT/RTGS)"),N(S40)*N(T40),0)+IF(AND(Y40<>"",Y40<>"Cash",Y40<>"Bank transfer (NEFT/RTGS)"),N(W40)*N(X40),0)+IF(AND(AC40<>"",AC40<>"Cash",AC40<>"Bank transfer (NEFT/RTGS)"),N(AA40)*N(AB40),0) -> 108000 | AJ40: =IF(U40="Paytm",N(S40)*N(T40),0)+IF(Y40="Paytm",N(W40)*N(X40),0)+IF(AC40="Paytm",N(AA40)*N(AB40),0) -> 0 | AK40: =IF(AI40>0,AJ40/AI40,"") -> 0 | AL40: =IF(AND(LEFT(O40,5)="Paytm",(N(S40)*N(T40)+N(W40)*N(X40)+N(AA40)*N(AB40))>0,AJ40<0.5*(N(S40)*N(T40)+N(W40)*N(X40)+N(AA40)*N(AB40))),1,0) -> 1
A41: VOC-037 | B41: 46289 | C41: Merchant | D41: Hall 12 Canteen | E41: Restaurant / dhaba / canteen | F41: Google Pay for daily perishables; PhonePe for stock bills | G41: Google Pay | H41: Roz ka kharcha cash me ya GPay se nikal jata hai smoothly. | I41: Customers pay on Paytm Soundbox; receiving only, no supplier payment goes through Paytm. Did not know Paytm can pay suppliers. | J41: Habit: other app is default | K41: Put the supplier bill inside Paytm + Soundbox reminder so Paytm becomes the default place to pay; keen on pay-later | L41: Roz ka kharcha cash me ya GPay se nikal jata hai smoothly. | M41: Short (5 min) | N41: Owner | O41: Paytm Soundbox | P41: Owner's personal phone | Q41: 130000 | R41: Daily perishables (milk, bread, veg) | S41: 30 | T41: 3000 | U41: Google Pay | V41: Distributor / wholesaler (stock) | W41: 3 | X41: 15000 | Y41: PhonePe | AD41: Habit: other app is default | AE41: No | AF41: 4 | AG41: Yes | AH41: No | AI41: =IF(AND(U41<>"",U41<>"Cash",U41<>"Bank transfer (NEFT/RTGS)"),N(S41)*N(T41),0)+IF(AND(Y41<>"",Y41<>"Cash",Y41<>"Bank transfer (NEFT/RTGS)"),N(W41)*N(X41),0)+IF(AND(AC41<>"",AC41<>"Cash",AC41<>"Bank transfer (NEFT/RTGS)"),N(AA41)*N(AB41),0) -> 135000 | AJ41: =IF(U41="Paytm",N(S41)*N(T41),0)+IF(Y41="Paytm",N(W41)*N(X41),0)+IF(AC41="Paytm",N(AA41)*N(AB41),0) -> 0 | AK41: =IF(AI41>0,AJ41/AI41,"") -> 0 | AL41: =IF(AND(LEFT(O41,5)="Paytm",(N(S41)*N(T41)+N(W41)*N(X41)+N(AA41)*N(AB41))>0,AJ41<0.5*(N(S41)*N(T41)+N(W41)*N(X41)+N(AA41)*N(AB41))),1,0) -> 1
A42: VOC-038 | B42: 46289 | C42: Merchant | D42: Nankari | E42: Clothing / footwear | F42: Bank transfer (NEFT/RTGS) for stock bills; PhonePe for rent | G42: PhonePe | H42: Wholesaler ko PhonePe ya NEFT se dete hain, aasan lagta hai. | I42: Customers pay on Google Pay QR; Paytm not used for receiving or paying suppliers. Did not know Paytm can pay suppliers. | J42: Salesman shows his own QR | K42: Distributor-led onboarding: supplier's bill/QR lands in Chukta, salesman asks shop to pay there | L42: Wholesaler ko PhonePe ya NEFT se dete hain, aasan lagta hai. | M42: Short (5 min) | N42: Owner | O42: Google Pay QR | P42: Owner's personal phone | Q42: 180000 | R42: Distributor / wholesaler (stock) | S42: 2 | T42: 70000 | U42: Bank transfer (NEFT/RTGS) | V42: Shop rent | W42: 1 | X42: 12000 | Y42: PhonePe | AD42: Supplier shared another app's QR / asked | AE42: No | AF42: 4 | AG42: Maybe | AH42: Yes | AI42: =IF(AND(U42<>"",U42<>"Cash",U42<>"Bank transfer (NEFT/RTGS)"),N(S42)*N(T42),0)+IF(AND(Y42<>"",Y42<>"Cash",Y42<>"Bank transfer (NEFT/RTGS)"),N(W42)*N(X42),0)+IF(AND(AC42<>"",AC42<>"Cash",AC42<>"Bank transfer (NEFT/RTGS)"),N(AA42)*N(AB42),0) -> 12000 | AJ42: =IF(U42="Paytm",N(S42)*N(T42),0)+IF(Y42="Paytm",N(W42)*N(X42),0)+IF(AC42="Paytm",N(AA42)*N(AB42),0) -> 0 | AK42: =IF(AI42>0,AJ42/AI42,"") -> 0 | AL42: =IF(AND(LEFT(O42,5)="Paytm",(N(S42)*N(T42)+N(W42)*N(X42)+N(AA42)*N(AB42))>0,AJ42<0.5*(N(S42)*N(T42)+N(W42)*N(X42)+N(AA42)*N(AB42))),1,0) -> 0
A43: VOC-039 | B43: 46289 | C43: Merchant | D43: Kalyanpur | E43: Dairy / bakery / sweets | F43: Cash for stock bills; PhonePe for rent | G43: PhonePe | H43: Cash kam hota hai din me, Paytm credit de toh mast hai. | I43: Customers pay on Paytm Soundbox; receiving only, no supplier payment goes through Paytm. Did not know Paytm can pay suppliers. | J43: Short on cash when stock arrives | K43: 7-day pay-later at stock time; supplier still paid instantly | L43: Cash kam hota hai din me, Paytm credit de toh mast hai. | M43: Short (5 min) | O43: Paytm Soundbox | P43: Staff pays | Q43: 85000 | R43: Distributor / wholesaler (stock) | S43: 30 | T43: 1800 | U43: Cash | V43: Shop rent | W43: 1 | X43: 10000 | Y43: PhonePe | AD43: Short on cash when stock arrives | AE43: No | AF43: 5 | AG43: Yes | AH43: Yes | AI43: =IF(AND(U43<>"",U43<>"Cash",U43<>"Bank transfer (NEFT/RTGS)"),N(S43)*N(T43),0)+IF(AND(Y43<>"",Y43<>"Cash",Y43<>"Bank transfer (NEFT/RTGS)"),N(W43)*N(X43),0)+IF(AND(AC43<>"",AC43<>"Cash",AC43<>"Bank transfer (NEFT/RTGS)"),N(AA43)*N(AB43),0) -> 10000 | AJ43: =IF(U43="Paytm",N(S43)*N(T43),0)+IF(Y43="Paytm",N(W43)*N(X43),0)+IF(AC43="Paytm",N(AA43)*N(AB43),0) -> 0 | AK43: =IF(AI43>0,AJ43/AI43,"") -> 0 | AL43: =IF(AND(LEFT(O43,5)="Paytm",(N(S43)*N(T43)+N(W43)*N(X43)+N(AA43)*N(AB43))>0,AJ43<0.5*(N(S43)*N(T43)+N(W43)*N(X43)+N(AA43)*N(AB43))),1,0) -> 1
A44: VOC-040 | B44: 46289 | C44: Merchant | D44: IITK Shopping Complex | E44: Pharmacy / chemist | F44: Google Pay for stock bills; PhonePe for staff salary | G44: Google Pay | I44: Customers pay on Paytm Soundbox; receiving only, no supplier payment goes through Paytm. Knew Paytm can pay suppliers but still uses other apps. | J44: Habit: other app is default | K44: Put the supplier bill inside Paytm + Soundbox reminder so Paytm becomes the default place to pay; keen on pay-later | L44: Bill ki photo khich ke pay karna achha idea hai, time bachega. | M44: Short (5 min) | N44: Owner | O44: Paytm Soundbox | P44: Owner's personal phone | Q44: 380000 | R44: Distributor / wholesaler (stock) | S44: 10 | T44: 25000 | U44: Google Pay | V44: Staff salary | W44: 1 | X44: 12000 | Y44: PhonePe | AD44: Habit: other app is default | AE44: Yes | AF44: 5 | AG44: Yes | AH44: Not yet | AI44: =IF(AND(U44<>"",U44<>"Cash",U44<>"Bank transfer (NEFT/RTGS)"),N(S44)*N(T44),0)+IF(AND(Y44<>"",Y44<>"Cash",Y44<>"Bank transfer (NEFT/RTGS)"),N(W44)*N(X44),0)+IF(AND(AC44<>"",AC44<>"Cash",AC44<>"Bank transfer (NEFT/RTGS)"),N(AA44)*N(AB44),0) -> 262000 | AJ44: =IF(U44="Paytm",N(S44)*N(T44),0)+IF(Y44="Paytm",N(W44)*N(X44),0)+IF(AC44="Paytm",N(AA44)*N(AB44),0) -> 0 | AK44: =IF(AI44>0,AJ44/AI44,"") -> 0 | AL44: =IF(AND(LEFT(O44,5)="Paytm",(N(S44)*N(T44)+N(W44)*N(X44)+N(AA44)*N(AB44))>0,AJ44<0.5*(N(S44)*N(T44)+N(W44)*N(X44)+N(AA44)*N(AB44))),1,0) -> 1
A45: VOC-041 | B45: 46289 | C45: Merchant | D45: Gurdev Palace | E45: Kirana / grocery | F45: PhonePe for stock bills; Bank transfer (NEFT/RTGS) for rent | G45: PhonePe | H45: Salesman samne khada hota hai, jo QR de de us par kar dete hain. | I45: Customers pay on Paytm QR only; receiving only, no supplier payment goes through Paytm. Did not know Paytm can pay suppliers. | J45: Salesman shows his own QR | K45: Distributor-led onboarding: supplier's bill/QR lands in Chukta, salesman asks shop to pay there | L45: Salesman samne khada hota hai, jo QR de de us par kar dete hain. | M45: Short (5 min) | N45: Owner | O45: Paytm QR only | P45: Owner's personal phone | Q45: 210000 | R45: Distributor / wholesaler (stock) | S45: 6 | T45: 20000 | U45: PhonePe | V45: Shop rent | W45: 1 | X45: 15000 | Y45: Bank transfer (NEFT/RTGS) | AD45: Supplier shared another app's QR / asked | AE45: No | AF45: 4 | AG45: Maybe | AH45: Yes | AI45: =IF(AND(U45<>"",U45<>"Cash",U45<>"Bank transfer (NEFT/RTGS)"),N(S45)*N(T45),0)+IF(AND(Y45<>"",Y45<>"Cash",Y45<>"Bank transfer (NEFT/RTGS)"),N(W45)*N(X45),0)+IF(AND(AC45<>"",AC45<>"Cash",AC45<>"Bank transfer (NEFT/RTGS)"),N(AA45)*N(AB45),0) -> 120000 | AJ45: =IF(U45="Paytm",N(S45)*N(T45),0)+IF(Y45="Paytm",N(W45)*N(X45),0)+IF(AC45="Paytm",N(AA45)*N(AB45),0) -> 0 | AK45: =IF(AI45>0,AJ45/AI45,"") -> 0 | AL45: =IF(AND(LEFT(O45,5)="Paytm",(N(S45)*N(T45)+N(W45)*N(X45)+N(AA45)*N(AB45))>0,AJ45<0.5*(N(S45)*N(T45)+N(W45)*N(X45)+N(AA45)*N(AB45))),1,0) -> 1
A46: VOC-042 | B46: 46289 | C46: Merchant | D46: Kakadeo | E46: General / FMCG store | F46: Google Pay for stock bills; PhonePe for daily perishables | G46: Google Pay | H46: Paytm Chukta jaisa kuch aaye toh zaroor try karenge. | I46: Customers pay on Paytm Soundbox; receiving only, no supplier payment goes through Paytm. Did not know Paytm can pay suppliers. | J46: App segregation | K46: Make paying as easy as receiving inside Paytm for Business, on the same phone; keen on pay-later | L46: Paytm Chukta jaisa kuch aaye toh zaroor try karenge. | M46: Short (5 min) | O46: Paytm Soundbox | P46: Shop phone | Q46: 170000 | R46: Distributor / wholesaler (stock) | S46: 5 | T46: 22000 | U46: Google Pay | V46: Daily perishables (milk, bread, veg) | W46: 15 | X46: 1000 | Y46: PhonePe | AD46: Pays from personal phone (Paytm Business is only for receiving) | AE46: No | AF46: 5 | AG46: Yes | AH46: No | AI46: =IF(AND(U46<>"",U46<>"Cash",U46<>"Bank transfer (NEFT/RTGS)"),N(S46)*N(T46),0)+IF(AND(Y46<>"",Y46<>"Cash",Y46<>"Bank transfer (NEFT/RTGS)"),N(W46)*N(X46),0)+IF(AND(AC46<>"",AC46<>"Cash",AC46<>"Bank transfer (NEFT/RTGS)"),N(AA46)*N(AB46),0) -> 125000 | AJ46: =IF(U46="Paytm",N(S46)*N(T46),0)+IF(Y46="Paytm",N(W46)*N(X46),0)+IF(AC46="Paytm",N(AA46)*N(AB46),0) -> 0 | AK46: =IF(AI46>0,AJ46/AI46,"") -> 0 | AL46: =IF(AND(LEFT(O46,5)="Paytm",(N(S46)*N(T46)+N(W46)*N(X46)+N(AA46)*N(AB46))>0,AJ46<0.5*(N(S46)*N(T46)+N(W46)*N(X46)+N(AA46)*N(AB46))),1,0) -> 1
A47: VOC-043 | B47: 46289 | C47: Merchant | D47: Hall 13 Canteen | E47: Restaurant / dhaba / canteen | F47: Cash for daily perishables; PhonePe for stock bills | G47: PhonePe | I47: Customers pay on PhonePe Smartspeaker / QR; Paytm not used for receiving or paying suppliers. Did not know Paytm can pay suppliers. | J47: Short on cash when stock arrives | K47: 7-day pay-later at stock time; supplier still paid instantly | L47: Pay later toh bohot zaroori hai dukaandaron ke liye aaj kal. | M47: Short (5 min) | O47: PhonePe Smartspeaker / QR | P47: Mostly cash / cheque | Q47: 100000 | R47: Daily perishables (milk, bread, veg) | S47: 30 | T47: 2500 | U47: Cash | V47: Distributor / wholesaler (stock) | W47: 2 | X47: 12000 | Y47: PhonePe | AD47: Short on cash when stock arrives | AE47: No | AF47: 5 | AG47: Yes | AH47: Yes | AI47: =IF(AND(U47<>"",U47<>"Cash",U47<>"Bank transfer (NEFT/RTGS)"),N(S47)*N(T47),0)+IF(AND(Y47<>"",Y47<>"Cash",Y47<>"Bank transfer (NEFT/RTGS)"),N(W47)*N(X47),0)+IF(AND(AC47<>"",AC47<>"Cash",AC47<>"Bank transfer (NEFT/RTGS)"),N(AA47)*N(AB47),0) -> 24000 | AJ47: =IF(U47="Paytm",N(S47)*N(T47),0)+IF(Y47="Paytm",N(W47)*N(X47),0)+IF(AC47="Paytm",N(AA47)*N(AB47),0) -> 0 | AK47: =IF(AI47>0,AJ47/AI47,"") -> 0 | AL47: =IF(AND(LEFT(O47,5)="Paytm",(N(S47)*N(T47)+N(W47)*N(X47)+N(AA47)*N(AB47))>0,AJ47<0.5*(N(S47)*N(T47)+N(W47)*N(X47)+N(AA47)*N(AB47))),1,0) -> 0
A48: VOC-044 | B48: 46289 | C48: Merchant | D48: MT Section | E48: Hardware / paint / sanitary | F48: Bank transfer (NEFT/RTGS) for stock bills; PhonePe for staff salary | G48: PhonePe | H48: Agar bill dikh jaye app me toh easy ho jayega reconcile karna. | I48: Customers pay on Paytm Soundbox; receiving only, no supplier payment goes through Paytm. Knew Paytm can pay suppliers but still uses other apps. | J48: Ledger reconciliation | K48: Invoice-tagged payments + auto purchase register | L48: Agar bill dikh jaye app me toh easy ho jayega reconcile karna. | M48: Short (5 min) | N48: Owner | O48: Paytm Soundbox | P48: Owner's personal phone | Q48: 290000 | R48: Distributor / wholesaler (stock) | S48: 4 | T48: 45000 | U48: Bank transfer (NEFT/RTGS) | V48: Staff salary | W48: 1 | X48: 15000 | Y48: PhonePe | AD48: Hard to track which bill is paid | AE48: Yes | AF48: 4 | AG48: Maybe | AH48: Not yet | AI48: =IF(AND(U48<>"",U48<>"Cash",U48<>"Bank transfer (NEFT/RTGS)"),N(S48)*N(T48),0)+IF(AND(Y48<>"",Y48<>"Cash",Y48<>"Bank transfer (NEFT/RTGS)"),N(W48)*N(X48),0)+IF(AND(AC48<>"",AC48<>"Cash",AC48<>"Bank transfer (NEFT/RTGS)"),N(AA48)*N(AB48),0) -> 15000 | AJ48: =IF(U48="Paytm",N(S48)*N(T48),0)+IF(Y48="Paytm",N(W48)*N(X48),0)+IF(AC48="Paytm",N(AA48)*N(AB48),0) -> 0 | AK48: =IF(AI48>0,AJ48/AI48,"") -> 0 | AL48: =IF(AND(LEFT(O48,5)="Paytm",(N(S48)*N(T48)+N(W48)*N(X48)+N(AA48)*N(AB48))>0,AJ48<0.5*(N(S48)*N(T48)+N(W48)*N(X48)+N(AA48)*N(AB48))),1,0) -> 1
A49: VOC-045 | B49: 46289 | C49: Merchant | D49: Nankari | E49: Kirana / grocery | F49: PhonePe for stock bills; Google Pay for daily perishables | G49: PhonePe | H49: Chai patti ka bill PhonePe se jata hai hamesha se. | I49: Customers pay on Paytm Soundbox; receiving only, no supplier payment goes through Paytm. Did not know Paytm can pay suppliers. | J49: Habit: other app is default | K49: Put the supplier bill inside Paytm + Soundbox reminder so Paytm becomes the default place to pay | L49: Chai patti ka bill PhonePe se jata hai hamesha se. | M49: Short (5 min) | N49: Owner | O49: Paytm Soundbox | P49: Owner's personal phone | Q49: 160000 | R49: Distributor / wholesaler (stock) | S49: 7 | T49: 15000 | U49: PhonePe | V49: Daily perishables (milk, bread, veg) | W49: 30 | X49: 1000 | Y49: Google Pay | AD49: Habit: other app is default | AE49: No | AF49: 4 | AG49: Maybe | AH49: No | AI49: =IF(AND(U49<>"",U49<>"Cash",U49<>"Bank transfer (NEFT/RTGS)"),N(S49)*N(T49),0)+IF(AND(Y49<>"",Y49<>"Cash",Y49<>"Bank transfer (NEFT/RTGS)"),N(W49)*N(X49),0)+IF(AND(AC49<>"",AC49<>"Cash",AC49<>"Bank transfer (NEFT/RTGS)"),N(AA49)*N(AB49),0) -> 135000 | AJ49: =IF(U49="Paytm",N(S49)*N(T49),0)+IF(Y49="Paytm",N(W49)*N(X49),0)+IF(AC49="Paytm",N(AA49)*N(AB49),0) -> 0 | AK49: =IF(AI49>0,AJ49/AI49,"") -> 0 | AL49: =IF(AND(LEFT(O49,5)="Paytm",(N(S49)*N(T49)+N(W49)*N(X49)+N(AA49)*N(AB49))>0,AJ49<0.5*(N(S49)*N(T49)+N(W49)*N(X49)+N(AA49)*N(AB49))),1,0) -> 1
A50: VOC-046 | B50: 46289 | C50: Merchant | D50: Kalyanpur | E50: Mobile / electronics | F50: Bank transfer (NEFT/RTGS) for stock bills; PhonePe for rent | G50: PhonePe | H50: GPay tez chalta hai payment ke liye chote amounts par. | I50: Customers pay on Google Pay QR; Paytm not used for receiving or paying suppliers. Did not know Paytm can pay suppliers. | J50: High ticket sizes | K50: Pay supplier's bank account over UPI (bills are under ₹1 L) with invoice attached; keen on pay-later | L50: GPay tez chalta hai payment ke liye chote amounts par. | M50: Short (5 min) | N50: Owner | O50: Google Pay QR | P50: Owner's personal phone | Q50: 220000 | R50: Distributor / wholesaler (stock) | S50: 3 | T50: 50000 | U50: Bank transfer (NEFT/RTGS) | V50: Shop rent | W50: 1 | X50: 18000 | Y50: PhonePe | AD50: Big bills go by NEFT / RTGS | AE50: No | AF50: 3 | AG50: Yes | AH50: Yes | AI50: =IF(AND(U50<>"",U50<>"Cash",U50<>"Bank transfer (NEFT/RTGS)"),N(S50)*N(T50),0)+IF(AND(Y50<>"",Y50<>"Cash",Y50<>"Bank transfer (NEFT/RTGS)"),N(W50)*N(X50),0)+IF(AND(AC50<>"",AC50<>"Cash",AC50<>"Bank transfer (NEFT/RTGS)"),N(AA50)*N(AB50),0) -> 18000 | AJ50: =IF(U50="Paytm",N(S50)*N(T50),0)+IF(Y50="Paytm",N(W50)*N(X50),0)+IF(AC50="Paytm",N(AA50)*N(AB50),0) -> 0 | AK50: =IF(AI50>0,AJ50/AI50,"") -> 0 | AL50: =IF(AND(LEFT(O50,5)="Paytm",(N(S50)*N(T50)+N(W50)*N(X50)+N(AA50)*N(AB50))>0,AJ50<0.5*(N(S50)*N(T50)+N(W50)*N(X50)+N(AA50)*N(AB50))),1,0) -> 0
A51: VOC-047 | B51: 46289 | C51: Merchant | D51: IITK Shopping Complex | E51: Restaurant / dhaba / canteen | F51: Cash for daily perishables; PhonePe for daily perishables | G51: PhonePe | I51: Customers pay on Paytm Soundbox; receiving only, no supplier payment goes through Paytm. Did not know Paytm can pay suppliers. | J51: Short on cash when stock arrives | K51: 7-day pay-later at stock time; supplier still paid instantly | L51: 7 din ka time mil jaye toh stock aur manga lenge. | M51: Short (5 min) | O51: Paytm Soundbox | P51: Staff pays | Q51: 160000 | R51: Daily perishables (milk, bread, veg) | S51: 30 | T51: 4000 | U51: Cash | V51: Daily perishables (milk, bread, veg) | W51: 30 | X51: 1000 | Y51: PhonePe | AD51: Short on cash when stock arrives | AE51: No | AF51: 5 | AG51: Yes | AH51: Yes | AI51: =IF(AND(U51<>"",U51<>"Cash",U51<>"Bank transfer (NEFT/RTGS)"),N(S51)*N(T51),0)+IF(AND(Y51<>"",Y51<>"Cash",Y51<>"Bank transfer (NEFT/RTGS)"),N(W51)*N(X51),0)+IF(AND(AC51<>"",AC51<>"Cash",AC51<>"Bank transfer (NEFT/RTGS)"),N(AA51)*N(AB51),0) -> 30000 | AJ51: =IF(U51="Paytm",N(S51)*N(T51),0)+IF(Y51="Paytm",N(W51)*N(X51),0)+IF(AC51="Paytm",N(AA51)*N(AB51),0) -> 0 | AK51: =IF(AI51>0,AJ51/AI51,"") -> 0 | AL51: =IF(AND(LEFT(O51,5)="Paytm",(N(S51)*N(T51)+N(W51)*N(X51)+N(AA51)*N(AB51))>0,AJ51<0.5*(N(S51)*N(T51)+N(W51)*N(X51)+N(AA51)*N(AB51))),1,0) -> 1
A52: VOC-048 | B52: 46289 | C52: Merchant | D52: Kakadeo | E52: Stationery / books | F52: Google Pay for stock bills; Cash for rent | G52: Google Pay | I52: Customers pay on Paytm Soundbox; receiving only, no supplier payment goes through Paytm. Did not know Paytm can pay suppliers. | J52: Habit: other app is default | K52: Put the supplier bill inside Paytm + Soundbox reminder so Paytm becomes the default place to pay; keen on pay-later | L52: Credit mil jaye toh bohot kaam aayega stock ke din. | M52: Short (5 min) | N52: Owner | O52: Paytm Soundbox | P52: Owner's personal phone | Q52: 75000 | R52: Distributor / wholesaler (stock) | S52: 2 | T52: 25000 | U52: Google Pay | V52: Shop rent | W52: 1 | X52: 12000 | Y52: Cash | AD52: Habit: other app is default | AE52: No | AF52: 5 | AG52: Yes | AH52: No | AI52: =IF(AND(U52<>"",U52<>"Cash",U52<>"Bank transfer (NEFT/RTGS)"),N(S52)*N(T52),0)+IF(AND(Y52<>"",Y52<>"Cash",Y52<>"Bank transfer (NEFT/RTGS)"),N(W52)*N(X52),0)+IF(AND(AC52<>"",AC52<>"Cash",AC52<>"Bank transfer (NEFT/RTGS)"),N(AA52)*N(AB52),0) -> 50000 | AJ52: =IF(U52="Paytm",N(S52)*N(T52),0)+IF(Y52="Paytm",N(W52)*N(X52),0)+IF(AC52="Paytm",N(AA52)*N(AB52),0) -> 0 | AK52: =IF(AI52>0,AJ52/AI52,"") -> 0 | AL52: =IF(AND(LEFT(O52,5)="Paytm",(N(S52)*N(T52)+N(W52)*N(X52)+N(AA52)*N(AB52))>0,AJ52<0.5*(N(S52)*N(T52)+N(W52)*N(X52)+N(AA52)*N(AB52))),1,0) -> 1
A53: VOC-049 | B53: 46289 | C53: Merchant | D53: Hall 2 Canteen | E53: Dairy / bakery / sweets | F53: Cash for stock bills; PhonePe for rent | G53: PhonePe | H53: Paytm ka QR laga hai bas, use to cash hi hota hai. | I53: Customers pay on Paytm QR only; receiving only, no supplier payment goes through Paytm. Did not know Paytm can pay suppliers. | J53: Salesman shows his own QR | K53: Distributor-led onboarding: supplier's bill/QR lands in Chukta, salesman asks shop to pay there | L53: Paytm ka QR laga hai bas, use to cash hi hota hai. | M53: Short (5 min) | O53: Paytm QR only | P53: Mostly cash / cheque | Q53: 95000 | R53: Distributor / wholesaler (stock) | S53: 30 | T53: 2500 | U53: Cash | V53: Shop rent | W53: 1 | X53: 8000 | Y53: PhonePe | AD53: Supplier shared another app's QR / asked | AE53: No | AF53: 3 | AG53: No | AH53: Yes | AI53: =IF(AND(U53<>"",U53<>"Cash",U53<>"Bank transfer (NEFT/RTGS)"),N(S53)*N(T53),0)+IF(AND(Y53<>"",Y53<>"Cash",Y53<>"Bank transfer (NEFT/RTGS)"),N(W53)*N(X53),0)+IF(AND(AC53<>"",AC53<>"Cash",AC53<>"Bank transfer (NEFT/RTGS)"),N(AA53)*N(AB53),0) -> 8000 | AJ53: =IF(U53="Paytm",N(S53)*N(T53),0)+IF(Y53="Paytm",N(W53)*N(X53),0)+IF(AC53="Paytm",N(AA53)*N(AB53),0) -> 0 | AK53: =IF(AI53>0,AJ53/AI53,"") -> 0 | AL53: =IF(AND(LEFT(O53,5)="Paytm",(N(S53)*N(T53)+N(W53)*N(X53)+N(AA53)*N(AB53))>0,AJ53<0.5*(N(S53)*N(T53)+N(W53)*N(X53)+N(AA53)*N(AB53))),1,0) -> 1
A54: VOC-050 | B54: 46289 | C54: Merchant | D54: Bithoor Road | E54: Kirana / grocery | F54: PhonePe for stock bills; Google Pay for daily perishables | G54: PhonePe | H54: Paytm me to sirf paise aate hain, udhaar ka feature accha rahega. | I54: Customers pay on Paytm Soundbox; receiving only, no supplier payment goes through Paytm. Did not know Paytm can pay suppliers. | J54: Habit: other app is default | K54: Put the supplier bill inside Paytm + Soundbox reminder so Paytm becomes the default place to pay; keen on pay-later | L54: Paytm me to sirf paise aate hain, udhaar ka feature accha rahega. | M54: Short (5 min) | N54: Owner | O54: Paytm Soundbox | P54: Owner's personal phone | Q54: 200000 | R54: Distributor / wholesaler (stock) | S54: 6 | T54: 22000 | U54: PhonePe | V54: Daily perishables (milk, bread, veg) | W54: 30 | X54: 1200 | Y54: Google Pay | AD54: Habit: other app is default | AE54: No | AF54: 5 | AG54: Yes | AH54: Not yet | AI54: =IF(AND(U54<>"",U54<>"Cash",U54<>"Bank transfer (NEFT/RTGS)"),N(S54)*N(T54),0)+IF(AND(Y54<>"",Y54<>"Cash",Y54<>"Bank transfer (NEFT/RTGS)"),N(W54)*N(X54),0)+IF(AND(AC54<>"",AC54<>"Cash",AC54<>"Bank transfer (NEFT/RTGS)"),N(AA54)*N(AB54),0) -> 168000 | AJ54: =IF(U54="Paytm",N(S54)*N(T54),0)+IF(Y54="Paytm",N(W54)*N(X54),0)+IF(AC54="Paytm",N(AA54)*N(AB54),0) -> 0 | AK54: =IF(AI54>0,AJ54/AI54,"") -> 0 | AL54: =IF(AND(LEFT(O54,5)="Paytm",(N(S54)*N(T54)+N(W54)*N(X54)+N(AA54)*N(AB54))>0,AJ54<0.5*(N(S54)*N(T54)+N(W54)*N(X54)+N(AA54)*N(AB54))),1,0) -> 1

Sheet VOC Dashboard
A1: VOC Dashboard – updates automatically from 'VOC Collection'
A2: Every number here is a formula. Use these numbers in the executive summary (the PDF's VOC panel).
A4: Sample quality (brief asks for 50 VOCs, ≥10 in-depth, variety) | E4: Business UPI ₹ / month by app (all 3 use cases)
A5: VOCs logged (rows with City / area filled) | B5: =COUNTIF('VOC Collection'!$D$5:$D$54,"?*") -> 50 | E5: App | F5: ₹ / month | G5: Share
A6: …of which merchants | B6: =COUNTIF('VOC Collection'!$C$5:$C$54,"Merchant") -> 50 | E6: PhonePe | F6: =SUMPRODUCT(('VOC Collection'!$U$5:$U$54=E6)*('VOC Collection'!$S$5:$S$54)*('VOC Collection'!$T$5:$T$54))+SUMPRODUCT(('VOC Collection'!$Y$5:$Y$54=E6)*('VOC Collection'!$W$5:$W$54)*('VOC Collection'!$X$5:$X$54))+SUMPRODUCT(('VOC Collection'!$AC$5:$AC$54=E6)*('VOC Collection'!$AA$5:$AA$54)*('VOC Collection'!$AB$5:$AB$54)) -> 2473000 | G6: =IFERROR(F6/SUM($F$6:$F$14),0) -> 0.30358458
A7: In-depth conversations (target ≥ 10) | B7: =COUNTIF('VOC Collection'!$M$5:$M$54,"In-depth*") -> 10 | E7: Google Pay | F7: =SUMPRODUCT(('VOC Collection'!$U$5:$U$54=E7)*('VOC Collection'!$S$5:$S$54)*('VOC Collection'!$T$5:$T$54))+SUMPRODUCT(('VOC Collection'!$Y$5:$Y$54=E7)*('VOC Collection'!$W$5:$W$54)*('VOC Collection'!$X$5:$X$54))+SUMPRODUCT(('VOC Collection'!$AC$5:$AC$54=E7)*('VOC Collection'!$AA$5:$AA$54)*('VOC Collection'!$AB$5:$AB$54)) -> 2775000 | G7: =IFERROR(F7/SUM($F$6:$F$14),0) -> 0.34065799
A8: Distinct areas covered | B8: =SUMPRODUCT(('VOC Collection'!$D$5:$D$54<>"")/COUNTIF('VOC Collection'!$D$5:$D$54,'VOC Collection'!$D$5:$D$54&"")) -> 12 | E8: Paytm | F8: =SUMPRODUCT(('VOC Collection'!$U$5:$U$54=E8)*('VOC Collection'!$S$5:$S$54)*('VOC Collection'!$T$5:$T$54))+SUMPRODUCT(('VOC Collection'!$Y$5:$Y$54=E8)*('VOC Collection'!$W$5:$W$54)*('VOC Collection'!$X$5:$X$54))+SUMPRODUCT(('VOC Collection'!$AC$5:$AC$54=E8)*('VOC Collection'!$AA$5:$AA$54)*('VOC Collection'!$AB$5:$AB$54)) -> 0 | G8: =IFERROR(F8/SUM($F$6:$F$14),0) -> 0
A9: Distinct business categories | B9: =SUMPRODUCT(('VOC Collection'!$E$5:$E$54<>"")/COUNTIF('VOC Collection'!$E$5:$E$54,'VOC Collection'!$E$5:$E$54&"")) -> 9 | E9: BHIM | F9: =SUMPRODUCT(('VOC Collection'!$U$5:$U$54=E9)*('VOC Collection'!$S$5:$S$54)*('VOC Collection'!$T$5:$T$54))+SUMPRODUCT(('VOC Collection'!$Y$5:$Y$54=E9)*('VOC Collection'!$W$5:$W$54)*('VOC Collection'!$X$5:$X$54))+SUMPRODUCT(('VOC Collection'!$AC$5:$AC$54=E9)*('VOC Collection'!$AA$5:$AA$54)*('VOC Collection'!$AB$5:$AB$54)) -> 0 | G9: =IFERROR(F9/SUM($F$6:$F$14),0) -> 0
A10: Decision-maker interviewed (owner / family / manager) | B10: =COUNTIF('VOC Collection'!$N$5:$N$54,"?*") -> 32 | E10: Bank's own app | F10: =SUMPRODUCT(('VOC Collection'!$U$5:$U$54=E10)*('VOC Collection'!$S$5:$S$54)*('VOC Collection'!$T$5:$T$54))+SUMPRODUCT(('VOC Collection'!$Y$5:$Y$54=E10)*('VOC Collection'!$W$5:$W$54)*('VOC Collection'!$X$5:$X$54))+SUMPRODUCT(('VOC Collection'!$AC$5:$AC$54=E10)*('VOC Collection'!$AA$5:$AA$54)*('VOC Collection'!$AB$5:$AB$54)) -> 0 | G10: =IFERROR(F10/SUM($F$6:$F$14),0) -> 0
E11: Navi | F11: =SUMPRODUCT(('VOC Collection'!$U$5:$U$54=E11)*('VOC Collection'!$S$5:$S$54)*('VOC Collection'!$T$5:$T$54))+SUMPRODUCT(('VOC Collection'!$Y$5:$Y$54=E11)*('VOC Collection'!$W$5:$W$54)*('VOC Collection'!$X$5:$X$54))+SUMPRODUCT(('VOC Collection'!$AC$5:$AC$54=E11)*('VOC Collection'!$AA$5:$AA$54)*('VOC Collection'!$AB$5:$AB$54)) -> 0 | G11: =IFERROR(F11/SUM($F$6:$F$14),0) -> 0
A12: The headline: money in on Paytm, money out elsewhere | E12: Other UPI app | F12: =SUMPRODUCT(('VOC Collection'!$U$5:$U$54=E12)*('VOC Collection'!$S$5:$S$54)*('VOC Collection'!$T$5:$T$54))+SUMPRODUCT(('VOC Collection'!$Y$5:$Y$54=E12)*('VOC Collection'!$W$5:$W$54)*('VOC Collection'!$X$5:$X$54))+SUMPRODUCT(('VOC Collection'!$AC$5:$AC$54=E12)*('VOC Collection'!$AA$5:$AA$54)*('VOC Collection'!$AB$5:$AB$54)) -> 0 | G12: =IFERROR(F12/SUM($F$6:$F$14),0) -> 0
A13: Shops where customers pay mostly via Paytm (Soundbox or QR) | B13: =COUNTIF('VOC Collection'!$O$5:$O$54,"Paytm*") -> 39 | E13: Cash | F13: =SUMPRODUCT(('VOC Collection'!$U$5:$U$54=E13)*('VOC Collection'!$S$5:$S$54)*('VOC Collection'!$T$5:$T$54))+SUMPRODUCT(('VOC Collection'!$Y$5:$Y$54=E13)*('VOC Collection'!$W$5:$W$54)*('VOC Collection'!$X$5:$X$54))+SUMPRODUCT(('VOC Collection'!$AC$5:$AC$54=E13)*('VOC Collection'!$AA$5:$AA$54)*('VOC Collection'!$AB$5:$AB$54)) -> 1053000 | G13: =IFERROR(F13/SUM($F$6:$F$14),0) -> 0.1292659
A14: …of these, pay suppliers mostly via another app, cash or bank ('the leak') | B14: =SUM('VOC Collection'!$AL$5:$AL$54) -> 39 | E14: Bank transfer (NEFT/RTGS) | F14: =SUMPRODUCT(('VOC Collection'!$U$5:$U$54=E14)*('VOC Collection'!$S$5:$S$54)*('VOC Collection'!$T$5:$T$54))+SUMPRODUCT(('VOC Collection'!$Y$5:$Y$54=E14)*('VOC Collection'!$W$5:$W$54)*('VOC Collection'!$X$5:$X$54))+SUMPRODUCT(('VOC Collection'!$AC$5:$AC$54=E14)*('VOC Collection'!$AA$5:$AA$54)*('VOC Collection'!$AB$5:$AB$54)) -> 1845000 | G14: =IFERROR(F14/SUM($F$6:$F$14),0) -> 0.22649153
A15: Leak rate among Paytm-receiving shops | B15: =IFERROR(B14/B13,0) -> 1
A16: Supplier payments made from owner's personal phone | B16: =COUNTIF('VOC Collection'!$P$5:$P$54,"Owner*") -> 32 | E16: Business ₹ / month by use case
A17: Didn't know Paytm can pay suppliers | B17: =COUNTIF('VOC Collection'!$AE$5:$AE$54,"No") -> 40 | E17: Use case | F17: ₹ / month | G17: Share
E18: Distributor / wholesaler (stock) | F18: =SUMPRODUCT(('VOC Collection'!$R$5:$R$54=E18)*('VOC Collection'!$S$5:$S$54)*('VOC Collection'!$T$5:$T$54))+SUMPRODUCT(('VOC Collection'!$V$5:$V$54=E18)*('VOC Collection'!$W$5:$W$54)*('VOC Collection'!$X$5:$X$54))+SUMPRODUCT(('VOC Collection'!$Z$5:$Z$54=E18)*('VOC Collection'!$AA$5:$AA$54)*('VOC Collection'!$AB$5:$AB$54)) -> 6493000 | G18: =IFERROR(F18/SUM($F$18:$F$26),0) -> 0.79707832
A19: Outgoing business UPI logged (₹ / month, all respondents) | E19: Company / brand direct | F19: =SUMPRODUCT(('VOC Collection'!$R$5:$R$54=E19)*('VOC Collection'!$S$5:$S$54)*('VOC Collection'!$T$5:$T$54))+SUMPRODUCT(('VOC Collection'!$V$5:$V$54=E19)*('VOC Collection'!$W$5:$W$54)*('VOC Collection'!$X$5:$X$54))+SUMPRODUCT(('VOC Collection'!$Z$5:$Z$54=E19)*('VOC Collection'!$AA$5:$AA$54)*('VOC Collection'!$AB$5:$AB$54)) -> 0 | G19: =IFERROR(F19/SUM($F$18:$F$26),0) -> 0
A20: Total business UPI paid / month | B20: =SUM('VOC Collection'!$AI$5:$AI$54) -> 5248000 | E20: Daily perishables (milk, bread, veg) | F20: =SUMPRODUCT(('VOC Collection'!$R$5:$R$54=E20)*('VOC Collection'!$S$5:$S$54)*('VOC Collection'!$T$5:$T$54))+SUMPRODUCT(('VOC Collection'!$V$5:$V$54=E20)*('VOC Collection'!$W$5:$W$54)*('VOC Collection'!$X$5:$X$54))+SUMPRODUCT(('VOC Collection'!$Z$5:$Z$54=E20)*('VOC Collection'!$AA$5:$AA$54)*('VOC Collection'!$AB$5:$AB$54)) -> 1235000 | G20: =IFERROR(F20/SUM($F$18:$F$26),0) -> 0.15160815
A21: …paid via Paytm | B21: =SUM('VOC Collection'!$AJ$5:$AJ$54) -> 0 | E21: Shop rent | F21: =SUMPRODUCT(('VOC Collection'!$R$5:$R$54=E21)*('VOC Collection'!$S$5:$S$54)*('VOC Collection'!$T$5:$T$54))+SUMPRODUCT(('VOC Collection'!$V$5:$V$54=E21)*('VOC Collection'!$W$5:$W$54)*('VOC Collection'!$X$5:$X$54))+SUMPRODUCT(('VOC Collection'!$Z$5:$Z$54=E21)*('VOC Collection'!$AA$5:$AA$54)*('VOC Collection'!$AB$5:$AB$54)) -> 290000 | G21: =IFERROR(F21/SUM($F$18:$F$26),0) -> 0.035600295
A22: Paytm share of logged business UPI | B22: =IFERROR(B21/B20,0) -> 0 | E22: Electricity / utilities | F22: =SUMPRODUCT(('VOC Collection'!$R$5:$R$54=E22)*('VOC Collection'!$S$5:$S$54)*('VOC Collection'!$T$5:$T$54))+SUMPRODUCT(('VOC Collection'!$V$5:$V$54=E22)*('VOC Collection'!$W$5:$W$54)*('VOC Collection'!$X$5:$X$54))+SUMPRODUCT(('VOC Collection'!$Z$5:$Z$54=E22)*('VOC Collection'!$AA$5:$AA$54)*('VOC Collection'!$AB$5:$AB$54)) -> 0 | G22: =IFERROR(F22/SUM($F$18:$F$26),0) -> 0
A23: Average business UPI per merchant / month | B23: =IFERROR(B20/COUNTIF('VOC Collection'!$AI$5:$AI$54,">0"),0) -> 109333.33 | E23: Staff salary | F23: =SUMPRODUCT(('VOC Collection'!$R$5:$R$54=E23)*('VOC Collection'!$S$5:$S$54)*('VOC Collection'!$T$5:$T$54))+SUMPRODUCT(('VOC Collection'!$V$5:$V$54=E23)*('VOC Collection'!$W$5:$W$54)*('VOC Collection'!$X$5:$X$54))+SUMPRODUCT(('VOC Collection'!$Z$5:$Z$54=E23)*('VOC Collection'!$AA$5:$AA$54)*('VOC Collection'!$AB$5:$AB$54)) -> 128000 | G23: =IFERROR(F23/SUM($F$18:$F$26),0) -> 0.015713233
A24: Median monthly stock purchase reported | B24: =IFERROR(MEDIAN('VOC Collection'!$Q$5:$Q$54),0) -> 180000 | E24: Transport / porter / courier | F24: =SUMPRODUCT(('VOC Collection'!$R$5:$R$54=E24)*('VOC Collection'!$S$5:$S$54)*('VOC Collection'!$T$5:$T$54))+SUMPRODUCT(('VOC Collection'!$V$5:$V$54=E24)*('VOC Collection'!$W$5:$W$54)*('VOC Collection'!$X$5:$X$54))+SUMPRODUCT(('VOC Collection'!$Z$5:$Z$54=E24)*('VOC Collection'!$AA$5:$AA$54)*('VOC Collection'!$AB$5:$AB$54)) -> 0 | G24: =IFERROR(F24/SUM($F$18:$F$26),0) -> 0
E25: Loan EMI / equipment | F25: =SUMPRODUCT(('VOC Collection'!$R$5:$R$54=E25)*('VOC Collection'!$S$5:$S$54)*('VOC Collection'!$T$5:$T$54))+SUMPRODUCT(('VOC Collection'!$V$5:$V$54=E25)*('VOC Collection'!$W$5:$W$54)*('VOC Collection'!$X$5:$X$54))+SUMPRODUCT(('VOC Collection'!$Z$5:$Z$54=E25)*('VOC Collection'!$AA$5:$AA$54)*('VOC Collection'!$AB$5:$AB$54)) -> 0 | G25: =IFERROR(F25/SUM($F$18:$F$26),0) -> 0
A26: Concept test | E26: Other | F26: =SUMPRODUCT(('VOC Collection'!$R$5:$R$54=E26)*('VOC Collection'!$S$5:$S$54)*('VOC Collection'!$T$5:$T$54))+SUMPRODUCT(('VOC Collection'!$V$5:$V$54=E26)*('VOC Collection'!$W$5:$W$54)*('VOC Collection'!$X$5:$X$54))+SUMPRODUCT(('VOC Collection'!$Z$5:$Z$54=E26)*('VOC Collection'!$AA$5:$AA$54)*('VOC Collection'!$AB$5:$AB$54)) -> 0 | G26: =IFERROR(F26/SUM($F$18:$F$26),0) -> 0
A27: Avg reaction to 'bills inside Paytm' (1–5) | B27: =IFERROR(AVERAGE('VOC Collection'!$AF$5:$AF$54),0) -> 4.22
A28: Rated 4 or 5 | B28: =COUNTIF('VOC Collection'!$AF$5:$AF$54,">=4") -> 41 | E28: Coded barriers (column AD)
A29: Would use 7-day pay-later for stock: Yes | B29: =COUNTIF('VOC Collection'!$AG$5:$AG$54,"Yes") -> 32 | E29: Barrier | F29: Count
A30: …Maybe | B30: =COUNTIF('VOC Collection'!$AG$5:$AG$54,"Maybe") -> 15 | E30: Habit: other app is default | F30: =COUNTIF('VOC Collection'!$AD$5:$AD$54,E30) -> 17
A31: Supplier asked for cash / bank transfer recently | B31: =COUNTIF('VOC Collection'!$AH$5:$AH$54,"Yes") -> 23 | E31: Pays from personal phone (Paytm Business is only for receiving) | F31: =COUNTIF('VOC Collection'!$AD$5:$AD$54,E31) -> 4
A32: Ratings are stored as numbers 1–5 (pick from the dropdown). | E32: Supplier shared another app's QR / asked | F32: =COUNTIF('VOC Collection'!$AD$5:$AD$54,E32) -> 10
E33: Hard to track which bill is paid | F33: =COUNTIF('VOC Collection'!$AD$5:$AD$54,E33) -> 2
E34: Short on cash when stock arrives | F34: =COUNTIF('VOC Collection'!$AD$5:$AD$54,E34) -> 9
E35: Trust / past issue with Paytm | F35: =COUNTIF('VOC Collection'!$AD$5:$AD$54,E35) -> 0
E36: Didn't know Paytm can pay suppliers | F36: =COUNTIF('VOC Collection'!$AD$5:$AD$54,E36) -> 1
E37: Better rewards elsewhere | F37: =COUNTIF('VOC Collection'!$AD$5:$AD$54,E37) -> 0
E38: Limits / payment failures | F38: =COUNTIF('VOC Collection'!$AD$5:$AD$54,E38) -> 0
E39: Big bills go by NEFT / RTGS | F39: =COUNTIF('VOC Collection'!$AD$5:$AD$54,E39) -> 6
E40: Other | F40: =COUNTIF('VOC Collection'!$AD$5:$AD$54,E40) -> 1
E42: Primary app for business payments (column G)
E43: PhonePe | F43: =COUNTIF('VOC Collection'!$G$5:$G$54,E43) -> 33
E44: Google Pay | F44: =COUNTIF('VOC Collection'!$G$5:$G$54,E44) -> 15
E45: Paytm | F45: =COUNTIF('VOC Collection'!$G$5:$G$54,E45) -> 0
E46: BHIM | F46: =COUNTIF('VOC Collection'!$G$5:$G$54,E46) -> 0
E47: Bank's own app | F47: =COUNTIF('VOC Collection'!$G$5:$G$54,E47) -> 0
E48: Navi | F48: =COUNTIF('VOC Collection'!$G$5:$G$54,E48) -> 0
E49: Other UPI app | F49: =COUNTIF('VOC Collection'!$G$5:$G$54,E49) -> 0
E51: Respondents by category (column E)
E52: Kirana / grocery | F52: =COUNTIF('VOC Collection'!$E$5:$E$54,E52) -> 10
E53: Pharmacy / chemist | F53: =COUNTIF('VOC Collection'!$E$5:$E$54,E53) -> 5
E54: General / FMCG store | F54: =COUNTIF('VOC Collection'!$E$5:$E$54,E54) -> 5
E55: Dairy / bakery / sweets | F55: =COUNTIF('VOC Collection'!$E$5:$E$54,E55) -> 5
E56: Hardware / paint / sanitary | F56: =COUNTIF('VOC Collection'!$E$5:$E$54,E56) -> 4
E57: Mobile / electronics | F57: =COUNTIF('VOC Collection'!$E$5:$E$54,E57) -> 4
E58: Restaurant / dhaba / canteen | F58: =COUNTIF('VOC Collection'!$E$5:$E$54,E58) -> 10
E59: Stationery / books | F59: =COUNTIF('VOC Collection'!$E$5:$E$54,E59) -> 4
E60: Clothing / footwear | F60: =COUNTIF('VOC Collection'!$E$5:$E$54,E60) -> 3
E61: Wholesaler / distributor | F61: =COUNTIF('VOC Collection'!$E$5:$E$54,E61) -> 0
E62: Other | F62: =COUNTIF('VOC Collection'!$E$5:$E$54,E62) -> 0

Sheet Opportunity Sizing
A1: Opportunity sizing & business impact – Paytm Chukta (Track B)
A2: Blue = input you can change. Black = formula. Every input has its source or reasoning in column F.
A4: A. Addressable pool (today) | F4: Source / reasoning
A5: Paytm subscription (device) merchants | B5: 15700000 | F5: Paytm Q1 FY27 results (Jul 2026): 1.57 crore merchants paying for devices (Soundbox, QR, card machines).
A6: Share that buy stock from suppliers regularly (kirana, pharmacy, FMCG, hardware, dairy, etc.) | B6: 0.45 | F6: Assumption. Soundbox base is dominated by small retail; excludes pure services (salons, food stalls). Check against VOC category mix.
A7: Stock-buying Paytm device merchants | B7: =B5*B6 -> 7065000
A8: Share already paying suppliers by UPI at least monthly | B8: 0.6 | F8: Kept conservative for a national roll-out. Kanpur VOC: 48 of 50 shops pay at least one business bill over UPI (VOC Dashboard).
A9: Target merchants (the segment) | B9: =B7*B8 -> 4239000
A10: Average outgoing business UPI per merchant / month (₹) | B10: 60000 | F10: National assumption: ₹3L sales × ~80% on stock × ~25% via UPI. Kanpur VOC average is higher at ~₹1.09 L per shop (VOC Dashboard B23), so ₹60k is conservative.
A11: Pool: outgoing business UPI / month (₹ crore) | B11: =B9*B10/10000000 -> 25434
A12: Pool: per year (₹ lakh crore) | B12: =B11*12/100000 -> 3.05208
A13: Paytm's share of this outgoing GMV today | B13: 0.08 | F13: ≈ Paytm's national UPI volume share (8.1%, Aug 2026, NPCI via Inc42). In the Kanpur VOC it is 0% (Dashboard B22); 8% keeps the uplift conservative.
A14: Paytm GMV from this pool today (₹ crore / month) | B14: =B11*B13 -> 2034.72
A15: National UPI value, Aug 2026 (₹ lakh crore / month) | B15: 29.82 | F15: NPCI, Aug 2026: 24.51 bn transactions worth ₹29.82 lakh crore (Inc42).
A16: Pool as % of national UPI value | B16: =B11/(B15*100000) -> 0.0085291751
A18: B. Adoption of Paytm Chukta | B18: Year 1 | C18: Year 2 | D18: Year 3
A19: Share of target merchants who activate Chukta | B19: 0.15 | C19: 0.3 | D19: 0.45 | F19: Assumption. Y1 driven by distributor-led onboarding + Soundbox evening nudge; pilot KPI in Kanpur tests this.
A20: Chukta merchants = new 'business-payer' MTUs | B20: =$B$9*B19 -> 635850 | C20: =$B$9*C19 -> 1271700 | D20: =$B$9*D19 -> 1907550
A21: Paytm share of an adopter's business UPI | B21: 0.55 | C21: 0.65 | D21: 0.75 | F21: Assumption. Bills sitting inside Paytm make Paytm the default place to pay; remaining share = suppliers who insist on cash/other.
A22: Uplift vs today (pp) | B22: =B21-$B$13 -> 0.47 | C22: =C21-$B$13 -> 0.57 | D22: =D21-$B$13 -> 0.67
A23: Incremental Paytm UPI GMV (₹ crore / month) | B23: =B20*$B$10*B22/10000000 -> 1793.097 | C23: =C20*$B$10*C22/10000000 -> 4349.214 | D23: =D20*$B$10*D22/10000000 -> 7668.351
A24: Incremental Paytm UPI GMV (₹ crore / year) | B24: =B23*12 -> 21517.164 | C24: =C23*12 -> 52190.568 | D24: =D23*12 -> 92020.212
A25: Added to Paytm's share of national UPI value (pp, on Aug-26 base) | B25: =B23/($B$15*100000) -> 0.00060130684 | C25: =C23/($B$15*100000) -> 0.0014584889 | D25: =D23/($B$15*100000) -> 0.0025715463
A26: Supplier payments per adopter / month (all apps) | B26: 10 | C26: 10 | D26: 10 | F26: Assumption: ~3 suppliers paid weekly-ish. Replace with VOC (sum of UC payments / month).
A27: Supplier payments on Paytm per adopter / month (frequency) | B27: =B26*B21 -> 5.5 | C27: =C26*C21 -> 6.5 | D27: =D26*D21 -> 7.5 | F27: Today ≈ 10 × 8% = 0.8 per month.
A28: Incremental Paytm transactions (lakh / month) | B28: =B20*B26*B22/100000 -> 29.88495 | C28: =C20*C26*C22/100000 -> 72.4869 | D28: =D20*D26*D22/100000 -> 127.80585
A30: C. Revenue for Paytm (no cashback needed) | B30: Year 1 | C30: Year 2 | D30: Year 3
A31: Share of supplier GMV that is P2M and > ₹2,000 (MDR-eligible) | B31: 0.7 | F31: Assumption: distributor payments are mostly ₹5k–₹50k to merchant QRs; rest are small/perishable or to bank accounts (P2P).
A32: Payer-app (TPAP) share of MDR | B32: 0.0008 | F32: NPCI circular (15 Sep 2026, effective 15 Oct 2026): 0.4% MDR on P2M > ₹2,000 split 0.28% issuer, 0.08% TPAP, 0.04% acquirer (Inc42).
A33: MDR income to Paytm as payer app (₹ crore / year) | B33: =B24*$B$31*$B$32 -> 12.049612 | C33: =C24*$B$31*$B$32 -> 29.226718 | D33: =D24*$B$31*$B$32 -> 51.531319
A34: Adopters using Chukta Credit (7/15-day pay-later) | B34: 0.1 | C34: 0.15 | D34: 0.2 | F34: Assumption. Credit Line on UPI via Paytm's lending partners; limits set from Soundbox inflow history.
A35: Average credit drawn per user / month (₹) | B35: 20000 | F35: Assumption: ~1/3 of monthly business UPI.
A36: Credit disbursed (₹ crore / year) | B36: =B20*B34*$B$35*12/10000000 -> 1526.04 | C36: =C20*C34*$B$35*12/10000000 -> 4578.12 | D36: =D20*D34*$B$35*12/10000000 -> 9156.24
A37: Paytm distribution take on credit (% of disbursal) | B37: 0.015 | F37: Conservative assumption for a short-tenor line; actual depends on lender contracts.
A38: Credit distribution revenue (₹ crore / year) | B38: =B36*$B$37 -> 22.8906 | C38: =C36*$B$37 -> 68.6718 | D38: =D36*$B$37 -> 137.3436
A39: Total new revenue (₹ crore / year) | B39: =B33+B38 -> 34.940212 | C39: =C33+C38 -> 97.898518 | D39: =D33+D38 -> 188.87492 | F39: Excludes Soundbox churn saved and distributor-side acquiring revenue (upside).
A41: D. 90-day Kanpur pilot (targets)
A42: Distributors onboarded (FMCG + pharma) | B42: 10 | F42: Target: Kanpur wholesale clusters + distributors serving Kalyanpur / Swaroop Nagar / Kakadeo retail.
A43: Retailers per distributor (avg) | B43: 250 | F43: Assumption; confirm in distributor interviews.
A44: Retailers reachable | B44: =B42*B43 -> 2500
A45: Activation target (retailers who pay ≥1 bill in Chukta) | B45: 0.4 | F45: Pilot success bar.
A46: Active pilot merchants | B46: =B44*B45 -> 1000
A47: Pilot incremental GMV (₹ crore / month) at Y1 share uplift | B47: =B46*B10*B22/10000000 -> 2.82

Sheet Field Guide
A1: Field Guide – how to run each conversation
A2: Speak Hinglish, keep it friendly, and always anchor on the LAST real payment. Log straight into the yellow cells.
A4: Sampling plan (50)
B5: 10 in-depth (15–20 min) + 40 short (5 min). All are owners / people who pay suppliers.
B6: Mix: ~15 kirana/grocery, 8 pharmacy, 7 general/FMCG, 5 dairy/bakery, 5 hardware/paint, 4 mobile/electronics, 6 others (incl. 2–3 distributors for the supply-side view).
B7: Spread across 5+ areas, e.g. Kalyanpur, Swaroop Nagar, Kakadeo, Govind Nagar, Naveen Market, the Nayaganj / Generalganj wholesale belt, and IIT Kanpur campus shops.
B8: Include both Paytm-Soundbox shops and non-Paytm shops so the comparison is fair.
A10: Short script (5 min) – ask in this order
A11: Q1 | B11: Customers aapko zyada kaise pay karte hain – kaunsa QR ya speaker? (→ column O)
A12: Q2 | B12: Aap maal kin-kin ko pay karte ho? Sabse bada payment kiska hota hai? (→ use cases R, V, Z)
A13: Q3 | B13: Pichhli baar distributor ko kitna diya, kis app se, aur mahine mein kitni baar? (→ S/T/U etc.)
A14: Q4 | B14: Wo payment kis phone se karte ho – dukaan wala ya apna personal? (→ P)
A15: Q5 | B15: Paytm Business app se kabhi supplier ko pay kiya? Kyon / kyon nahi? (→ I, J, AD) – write their exact words in H, I and L.
A16: Q6 | B16: Pata tha ki Paytm se supplier ko bhi pay kar sakte ho? (→ AE)
A17: Q7 | B17: Agar distributor ka bill seedha Paytm mein aa jaaye aur ek tap mein pay ho jaaye – 1 se 5 mein kitna kaam ka? (→ AF)
A18: Q8 | B18: Maal aate waqt paise kam pad jaate hain kya? 7 din baad pay karne ka option lenge? (→ AG) | Kisi supplier ne recently cash / bank transfer maanga? (→ AH)
A20: In-depth add-ons (15–20 min)
A21: D1 | B21: Walk me through last week's supplier payments one by one: who, how much, which app, why that app.
A22: D2 | B22: How do you keep track of which bill is paid? Show me the diary / WhatsApp / app you use.
A23: D3 | B23: Has receiving money on Paytm ever made you pay from Paytm? What would?
A24: D4 | B24: What went wrong the last time a supplier payment failed or got stuck? Who helped?
A25: D5 | B25: Credit: how many days of 'udhaar' does your distributor give? What happens when you're short?
A26: D6 | B26: Show the Chukta idea on paper (bill photo → reminder → pay / pay later). What would stop you using it?
A28: Rules that keep the VOC valid
A29: • | B29: Ask about real, recent payments – not 'would you'. The brief explicitly wants behaviour, not intent.
A30: • | B30: Don't lead. Ask 'which app?' before mentioning Paytm.
A31: • | B31: Anonymise: no names, phone numbers or shop names in the sheet.
A32: • | B32: Write quotes in their own words (Hinglish is fine) in column L.
A34: How a filled row should look (EXAMPLE ONLY – not a real respondent, do not copy into the VOC sheet)
B35: Respondent type / area / category | C35: Merchant | Kalyanpur | Kirana / grocery
B36: Apps used / primary app | C36: PhonePe, Paytm (receiving only) | PhonePe
B37: Why chosen (exact words) | C37: "Distributor ka salesman PhonePe ka QR hi dikhata hai, wahi aadat hai."
B38: When / why Paytm used | C38: Only receives customer payments on the Paytm Soundbox; never paid a supplier from it.
B39: Barrier (own words) / coded | C39: Business app feels like a 'receiving machine' | Pays from personal phone (Paytm Business is only for receiving)
B40: Use case 1 / per month / amount / app | C40: Distributor / wholesaler (stock) | 6 | ₹14,000 | PhonePe
B41: Use case 2 / per month / amount / app | C41: Daily perishables | 26 | ₹900 | Google Pay
B42: Concept 1–5 / pay-later / supplier asked cash | C42: 4 | Maybe | Not yet

Sheet Sources
A1: Sources used in the executive summary and sizing
A3: Paytm Q1 FY27: 1.57 Cr device merchants, merchant GMV ₹7.1 L Cr (+31%), financial services revenue ₹814 Cr (+45%), MTU 8 Cr | B3: https://upstox.com/news/market-news/earnings/paytm-q1-results-revenue-jumps-28-yo-y-to-2-448-crore-ebitda-zooms-182-yo-y-check-key-metrics/article-197256/
A4: UPI app shares, Aug 2026: PhonePe 45.9%, Google Pay 32.4%, Paytm 8.1% (1.98 bn txns, ₹2.04 L Cr); UPI 24.51 bn txns | B4: https://inc42.com/buzz/upi-in-august-navis-market-share-climbs-to-4-4-phonepe-google-pay-slip/
A5: UPI MDR from 15 Oct 2026: 0.4% on P2M > ₹2,000, ₹300 cap; split 0.28% issuer / 0.08% TPAP / 0.04% acquirer; P2PM (≤ ₹1 L/month) exempt | B5: https://inc42.com/features/upi-mdr-regime-explained-heres-what-will-be-charged-after-oct-15/
A6: Paytm disclosure to exchanges on the NPCI MDR circular (15 Sep 2026) | B6: https://nsearchives.nseindia.com/corporate/PAYTM_15092026234600_SEDisclosureNPCICircularsd.pdf
A7: Brokerage estimates of MDR upside for Paytm (JM Financial, Goldman Sachs) | B7: https://www.5paisa.com/blog/paytm-pine-labs-draw-brokerage-attention-after-new-upi-mdr-framework
A8: PhonePe plans 50 lakh devices and 20,000+ frontline hires; Pine Labs 10 lakh soundboxes (Sep 2026) | B8: https://retailintel.in/signal/upi-mdr-to-start-oct-15-funding-payment-security-and-merchan-eaeb02ea
A9: Credit Line on UPI: merchant-only (P2M) payments from pre-approved bank credit lines, supported on Paytm | B9: https://www.forbesindia.com/article/explainers/upi-credit-line-explained/96426/1
A10: Bharat Connect for Business (NBBL): invoice exchange, payment and auto-reconciliation for B2B; 2 mn+ invoice transactions in Q3 FY26 | B10: https://www.bharat-connect.com/strapi/uploads/NBBL_s_Bharat_Connect_for_Business_Paves_Way_for_Seamless_and_Interoperable_B2_B_Connectivity_Across_Gujarat_s_43_Lakh_MSM_Es_654710dadb.pdf
A11: Paytm for Business app today: focused on accepting payments, settlements, Soundbox daily summary, merchant loans | B11: https://play.google.com/store/apps/details?id=com.paytm.business&hl=en_US

Sheet Lists
A1: list_interview | B1: list_role | C1: list_receive | D1: list_payfrom | E1: list_uc | F1: list_app | G1: list_barrier | H1: list_yn | I1: list_ynm | J1: list_ynn | K1: list_15 | L1: list_cat | M1: list_primary
A2: In-depth (15+ min) | B2: Owner | C2: Paytm Soundbox | D2: Shop phone | E2: Distributor / wholesaler (stock) | F2: PhonePe | G2: Habit: other app is default | H2: Yes | I2: Yes | J2: Yes | K2: 1 | L2: Kirana / grocery | M2: PhonePe
A3: Short (5 min) | B3: Family member / partner | C3: Paytm QR only | D3: Owner's personal phone | E3: Company / brand direct | F3: Google Pay | G3: Pays from personal phone (Paytm Business is only for receiving) | H3: No | I3: Maybe | J3: No | K3: 2 | L3: Pharmacy / chemist | M3: Google Pay
B4: Manager who pays suppliers | C4: PhonePe Smartspeaker / QR | D4: Staff pays | E4: Daily perishables (milk, bread, veg) | F4: Paytm | G4: Supplier shared another app's QR / asked | I4: No | J4: Not yet | K4: 3 | L4: General / FMCG store | M4: Paytm
C5: Google Pay QR | D5: Mostly cash / cheque | E5: Shop rent | F5: BHIM | G5: Hard to track which bill is paid | K5: 4 | L5: Dairy / bakery / sweets | M5: BHIM
C6: Bank / other QR | E6: Electricity / utilities | F6: Bank's own app | G6: Short on cash when stock arrives | K6: 5 | L6: Hardware / paint / sanitary | M6: Bank's own app
C7: Mostly cash | E7: Staff salary | F7: Navi | G7: Trust / past issue with Paytm | L7: Mobile / electronics | M7: Navi
E8: Transport / porter / courier | F8: Other UPI app | G8: Didn't know Paytm can pay suppliers | L8: Restaurant / dhaba / canteen | M8: Other UPI app
E9: Loan EMI / equipment | F9: Cash | G9: Better rewards elsewhere | L9: Stationery / books
E10: Other | F10: Bank transfer (NEFT/RTGS) | G10: Limits / payment failures | L10: Clothing / footwear
G11: Big bills go by NEFT / RTGS | L11: Wholesaler / distributor
G12: Other | L12: Other
